{
  "vanillatweaks:root": {
    "criteria": {
      "tick": "2021-12-29 20:54:39 +0100"
    },
    "done": true
  },
  "vanillatweaks:durability_ping": {
    "criteria": {
      "tick": "2021-12-29 20:54:39 +0100"
    },
    "done": true
  },
  "vanillatweaks:dragon_drops": {
    "criteria": {
      "tick": "2021-12-29 20:54:39 +0100"
    },
    "done": true
  },
  "minecraft:adventure/adventuring_time": {
    "criteria": {
      "minecraft:birch_forest": "2021-12-29 20:55:38 +0100",
      "minecraft:river": "2021-12-29 20:55:35 +0100",
      "minecraft:forest": "2021-12-29 20:56:32 +0100",
      "minecraft:jungle": "2021-12-29 20:55:39 +0100",
      "minecraft:old_growth_birch_forest": "2021-12-29 20:55:19 +0100",
      "minecraft:plains": "2021-12-29 20:54:39 +0100"
    },
    "done": false
  },
  "vanillatweaks:double_shulker_shells": {
    "criteria": {
      "tick": "2021-12-29 20:54:39 +0100"
    },
    "done": true
  },
  "DataVersion": 2865
}