{
  "global:thewii": {
    "criteria": {
      "trigger": "2024-08-31 14:19:22 +0100"
    },
    "done": true
  },
  "minecraft:recipes/decorations/crafting_table": {
    "criteria": {
      "unlock_right_away": "2024-08-31 14:19:22 +0100"
    },
    "done": true
  },
  "thewii:immersive/player/player_joined": {
    "criteria": {
      "joined": "2024-08-31 14:19:22 +0100"
    },
    "done": true
  },
  "global:root": {
    "criteria": {
      "trigger": "2024-08-31 14:19:22 +0100"
    },
    "done": true
  },
  "thewii:immersive/core/immersive-soundscapes": {
    "criteria": {
      "trigger": "2024-08-31 14:19:22 +0100"
    },
    "done": true
  },
  "incendium:technical/new_player": {
    "criteria": {
      "requirement": "2024-08-31 14:19:22 +0100"
    },
    "done": true
  },
  "minecraft:recipes/decorations/torch": {
    "criteria": {
      "has_stone_pickaxe": "2024-08-31 14:19:23 +0100"
    },
    "done": true
  },
  "minecraft:recipes/misc/charcoal": {
    "criteria": {
      "has_log": "2024-08-31 14:19:23 +0100"
    },
    "done": true
  },
  "minecraft:story/upgrade_tools": {
    "criteria": {
      "stone_pickaxe": "2024-08-31 14:19:23 +0100"
    },
    "done": true
  },
  "minecraft:recipes/decorations/chest": {
    "criteria": {
      "has_lots_of_items": "2024-08-31 14:19:23 +0100"
    },
    "done": true
  },
  "minecraft:recipes/building_blocks/oak_planks": {
    "criteria": {
      "has_logs": "2024-08-31 14:19:23 +0100"
    },
    "done": true
  },
  "minecraft:recipes/building_blocks/oak_wood": {
    "criteria": {
      "has_log": "2024-08-31 14:19:23 +0100"
    },
    "done": true
  },
  "incendium:technical/scroll_of_returning": {
    "criteria": {
      "log_spam_fixer": "2024-08-31 14:19:24 +0100"
    },
    "done": false
  },
  "incendium:technical/using/ragnarok": {
    "criteria": {
      "log_spam_fixer": "2024-08-31 14:19:24 +0100"
    },
    "done": false
  },
  "incendium:technical/using/trailblazer": {
    "criteria": {
      "log_spam_fixer": "2024-08-31 14:19:24 +0100"
    },
    "done": false
  },
  "incendium:technical/using/shield": {
    "criteria": {
      "log_spam_fixer": "2024-08-31 14:19:24 +0100"
    },
    "done": false
  },
  "minecraft:adventure/adventuring_time": {
    "criteria": {
      "minecraft:old_growth_pine_taiga": "2024-08-31 14:29:46 +0100",
      "minecraft:sunflower_plains": "2024-08-31 14:27:47 +0100",
      "minecraft:dark_forest": "2024-08-31 14:29:04 +0100",
      "minecraft:river": "2024-08-31 14:20:13 +0100",
      "minecraft:old_growth_spruce_taiga": "2024-08-31 14:28:29 +0100",
      "minecraft:old_growth_birch_forest": "2024-08-31 14:28:12 +0100",
      "minecraft:meadow": "2024-08-31 14:21:45 +0100",
      "minecraft:plains": "2024-08-31 14:27:50 +0100"
    },
    "done": false
  },
  "minecraft:recipes/transportation/mangrove_boat": {
    "criteria": {
      "in_water": "2024-08-31 14:20:14 +0100"
    },
    "done": true
  },
  "minecraft:recipes/transportation/acacia_boat": {
    "criteria": {
      "in_water": "2024-08-31 14:20:14 +0100"
    },
    "done": true
  },
  "minecraft:recipes/transportation/cherry_boat": {
    "criteria": {
      "in_water": "2024-08-31 14:20:14 +0100"
    },
    "done": true
  },
  "minecraft:recipes/transportation/bamboo_raft": {
    "criteria": {
      "in_water": "2024-08-31 14:20:14 +0100"
    },
    "done": true
  },
  "minecraft:recipes/transportation/spruce_boat": {
    "criteria": {
      "in_water": "2024-08-31 14:20:14 +0100"
    },
    "done": true
  },
  "minecraft:recipes/transportation/birch_boat": {
    "criteria": {
      "in_water": "2024-08-31 14:20:14 +0100"
    },
    "done": true
  },
  "minecraft:recipes/transportation/oak_boat": {
    "criteria": {
      "in_water": "2024-08-31 14:20:14 +0100"
    },
    "done": true
  },
  "minecraft:recipes/transportation/jungle_boat": {
    "criteria": {
      "in_water": "2024-08-31 14:20:14 +0100"
    },
    "done": true
  },
  "minecraft:recipes/transportation/dark_oak_boat": {
    "criteria": {
      "in_water": "2024-08-31 14:20:14 +0100"
    },
    "done": true
  },
  "minecraft:husbandry/balanced_diet": {
    "criteria": {
      "baked_potato": "2024-08-31 14:21:54 +0100"
    },
    "done": false
  },
  "minecraft:husbandry/root": {
    "criteria": {
      "consumed_item": "2024-08-31 14:21:54 +0100"
    },
    "done": true
  },
  "minecraft:adventure/root": {
    "criteria": {
      "killed_something": "2024-08-31 14:26:13 +0100"
    },
    "done": true
  },
  "dnl:entity/guardian_ghast/hurt": {
    "criteria": {
      "not_projectile": "2024-08-31 14:26:13 +0100"
    },
    "done": false
  },
  "minecraft:recipes/misc/black_dye": {
    "criteria": {
      "has_ink_sac": "2024-08-31 14:26:46 +0100"
    },
    "done": true
  },
  "incendium:technical/sentrys_wrath": {
    "criteria": {
      "log_spam_fixer": "2024-08-31 14:38:37 +0100"
    },
    "done": false
  },
  "incendium:technical/inventory/sentrys_wrath": {
    "criteria": {
      "log_spam_fixer": "2024-08-31 14:38:37 +0100"
    },
    "done": false
  },
  "incendium:technical/multiplex_crossbow": {
    "criteria": {
      "log_spam_fixer": "2024-08-31 14:38:37 +0100"
    },
    "done": false
  },
  "incendium:technical/feed_ghastling": {
    "criteria": {
      "log_spam_fixer": "2024-08-31 14:38:37 +0100"
    },
    "done": false
  },
  "incendium:technical/on_inventory_change": {
    "criteria": {
      "log_spam_fixer": "2024-08-31 14:38:37 +0100"
    },
    "done": false
  },
  "incendium:technical/on_player_hurt": {
    "criteria": {
      "requirement": "2024-08-31 14:38:36 +0100",
      "log_spam_fixer": "2024-08-31 14:38:37 +0100"
    },
    "done": true
  },
  "incendium:technical/firestorm": {
    "criteria": {
      "log_spam_fixer": "2024-08-31 14:38:37 +0100"
    },
    "done": false
  },
  "incendium:technical/holy_wrath": {
    "criteria": {
      "log_spam_fixer": "2024-08-31 14:38:37 +0100"
    },
    "done": false
  },
  "incendium:technical/on_block": {
    "criteria": {
      "log_spam_fixer": "2024-08-31 14:38:37 +0100"
    },
    "done": false
  },
  "incendium:technical/inventory/firestorm": {
    "criteria": {
      "log_spam_fixer": "2024-08-31 14:38:37 +0100"
    },
    "done": false
  },
  "incendium:technical/give_ghastling": {
    "criteria": {
      "log_spam_fixer": "2024-08-31 14:38:37 +0100"
    },
    "done": false
  },
  "incendium:technical/on_kill": {
    "criteria": {
      "log_spam_fixer": "2024-08-31 14:38:37 +0100"
    },
    "done": false
  },
  "minecraft:recipes/combat/leather_helmet": {
    "criteria": {
      "has_leather": "2024-08-31 14:28:06 +0100"
    },
    "done": true
  },
  "minecraft:recipes/combat/leather_leggings": {
    "criteria": {
      "has_leather": "2024-08-31 14:28:06 +0100"
    },
    "done": true
  },
  "minecraft:recipes/decorations/item_frame": {
    "criteria": {
      "has_leather": "2024-08-31 14:28:06 +0100"
    },
    "done": true
  },
  "minecraft:recipes/combat/leather_chestplate": {
    "criteria": {
      "has_leather": "2024-08-31 14:28:06 +0100"
    },
    "done": true
  },
  "minecraft:recipes/combat/leather_boots": {
    "criteria": {
      "has_leather": "2024-08-31 14:28:06 +0100"
    },
    "done": true
  },
  "minecraft:recipes/misc/leather_horse_armor": {
    "criteria": {
      "has_leather": "2024-08-31 14:28:06 +0100"
    },
    "done": true
  },
  "stellarity:events/on_death": {
    "criteria": {
      "requirement": "2024-08-31 14:38:36 +0100"
    },
    "done": true
  },
  "dnl:util/entity_hit_matching/on_hit": {
    "criteria": {
      "not_projectile": "2024-08-31 14:34:45 +0100",
      "is_projectile": "2024-08-31 14:34:45 +0100",
      "not_magic": "2024-08-31 14:34:45 +0100"
    },
    "done": false
  },
  "minecraft:adventure/totem_of_undying": {
    "criteria": {
      "used_totem": "2024-08-31 14:35:23 +0100"
    },
    "done": true
  },
  "DataVersion": 3465
}