{"stats":{"minecraft:mined":{"minecraft:bamboo":1},"minecraft:picked_up":{"minecraft:bamboo":7},"minecraft:custom":{"minecraft:jump":17,"minecraft:time_since_rest":4988,"minecraft:play_time":4988,"minecraft:leave_game":2,"minecraft:sprint_one_cm":10462,"minecraft:damage_taken":10,"minecraft:time_since_death":4988,"minecraft:walk_one_cm":19357,"minecraft:total_world_time":4988,"minecraft:talked_to_villager":1,"minecraft:fall_one_cm":546,"minecraft:fly_one_cm":785},"minecraft:used":{"minecraft:stone_axe":1}},"DataVersion":3120}