{"stats":{"minecraft:mined":{"minecraft:deepslate_redstone_ore":4,"minecraft:tuff":1,"minecraft:deepslate_diamond_ore":5,"minecraft:crafting_table":3,"minecraft:obsidian":4,"minecraft:copper_ore":106,"minecraft:deepslate_gold_ore":16,"minecraft:lapis_ore":11,"minecraft:oak_planks":1,"minecraft:diorite":4,"minecraft:spawner":1,"minecraft:furnace":2,"minecraft:iron_ore":49,"minecraft:sweet_berry_bush":6,"minecraft:andesite":1,"minecraft:bee_nest":1,"minecraft:deepslate_lapis_ore":9,"minecraft:grass":19,"minecraft:oak_log":5,"minecraft:pointed_dripstone":7,"minecraft:coal_ore":44,"minecraft:cocoa":1,"minecraft:deepslate_iron_ore":9,"minecraft:dripstone_block":7,"minecraft:dirt":2,"minecraft:bamboo":9,"minecraft:stone":138,"minecraft:gold_ore":1,"minecraft:deepslate":36},"minecraft:killed_by":{"minecraft:creeper":1},"minecraft:crafted":{"minecraft:oak_planks":20,"minecraft:crafting_table":1,"minecraft:wooden_pickaxe":1,"minecraft:furnace":1,"minecraft:diamond_pickaxe":1,"minecraft:stick":8,"minecraft:iron_ingot":24,"minecraft:iron_pickaxe":2,"minecraft:stone_pickaxe":1},"minecraft:used":{"minecraft:stone_sword":99,"minecraft:stone_pickaxe":96,"minecraft:oak_planks":2,"minecraft:shield":13,"minecraft:wooden_pickaxe":14,"minecraft:torch":1,"minecraft:crafting_table":3,"minecraft:diamond_pickaxe":109,"minecraft:iron_pickaxe":235,"minecraft:cobblestone":42,"minecraft:written_book":1,"minecraft:furnace":2},"minecraft:dropped":{"minecraft:cobbled_deepslate":33,"minecraft:tuff":1,"minecraft:dripstone_block":8,"minecraft:pointed_dripstone":7,"minecraft:feather":5,"minecraft:pumpkin_seeds":1,"minecraft:potato":1,"minecraft:iron_pickaxe":1,"minecraft:string":2,"minecraft:bone":1},"minecraft:killed":{"minecraft:pig":1,"minecraft:spider":1,"minecraft:creeper":2,"minecraft:skeleton":1,"minecraft:chicken":5,"minecraft:stray":2,"minecraft:cow":3},"minecraft:custom":{"minecraft:interact_with_furnace":8,"minecraft:mob_kills":17,"minecraft:interact_with_crafting_table":6,"minecraft:leave_game":3,"minecraft:time_since_death":19211,"minecraft:climb_one_cm":1205,"minecraft:time_since_rest":1986,"minecraft:sprint_one_cm":339687,"minecraft:damage_taken":1743,"minecraft:walk_one_cm":145247,"minecraft:damage_blocked_by_shield":540,"minecraft:drop":13,"minecraft:damage_dealt":1980,"minecraft:talked_to_villager":1,"minecraft:swim_one_cm":1527,"minecraft:fly_one_cm":189139,"minecraft:open_chest":4,"minecraft:crouch_one_cm":6056,"minecraft:play_time":62032,"minecraft:deaths":1,"minecraft:sneak_time":1921,"minecraft:walk_under_water_one_cm":1188,"minecraft:jump":903,"minecraft:walk_on_water_one_cm":1911,"minecraft:total_world_time":62032,"minecraft:fall_one_cm":20853,"minecraft:horse_one_cm":2476},"minecraft:picked_up":{"minecraft:crafting_table":3,"minecraft:feather":5,"minecraft:chicken":5,"minecraft:glow_ink_sac":2,"minecraft:andesite":1,"minecraft:leather":1,"minecraft:tuff":1,"minecraft:oak_log":5,"minecraft:gunpowder":2,"minecraft:lapis_lazuli":103,"minecraft:string":2,"minecraft:raw_copper":362,"minecraft:bone":1,"minecraft:cobbled_deepslate":38,"minecraft:raw_gold":17,"minecraft:beef":1,"minecraft:bamboo":87,"minecraft:oak_planks":1,"minecraft:furnace":2,"minecraft:raw_iron":59,"minecraft:dripstone_block":8,"minecraft:porkchop":2,"minecraft:pointed_dripstone":14,"minecraft:diorite":4,"minecraft:redstone":18,"minecraft:pumpkin_seeds":1,"minecraft:diamond":5,"minecraft:obsidian":4,"minecraft:coal":44,"minecraft:cobblestone":137}},"DataVersion":2865}