{"stats":{"minecraft:killed_by":{"minecraft:zombie_villager":1,"minecraft:ravager":4,"minecraft:zombie":4,"minecraft:warden":4,"minecraft:wither":1,"minecraft:ghast":7,"minecraft:drowned":2,"minecraft:skeleton":17,"minecraft:pillager":4,"minecraft:vindicator":21,"minecraft:vex":12,"minecraft:stray":1,"minecraft:guardian":5,"minecraft:evoker":1,"minecraft:creeper":5,"minecraft:piglin":2,"minecraft:blaze":1,"minecraft:player":197,"minecraft:spider":2,"minecraft:enderman":2,"minecraft:iron_golem":1,"minecraft:hoglin":2},"minecraft:picked_up":{"minecraft:lead":11,"minecraft:stone_slab":59,"minecraft:enchanted_book":28,"minecraft:purple_shulker_box":7,"minecraft:polished_deepslate":261,"minecraft:music_disc_cat":7,"minecraft:polished_blackstone_brick_stairs":1,"minecraft:string":905,"minecraft:pufferfish":24,"minecraft:shroomlight":25,"minecraft:sculk_shrieker":9,"minecraft:diamond_leggings":6,"minecraft:horn_coral_block":4,"minecraft:crimson_sign":11,"minecraft:spruce_pressure_plate":1,"minecraft:polished_blackstone_brick_slab":39,"minecraft:jukebox":4,"minecraft:acacia_log":73,"minecraft:cut_copper_stairs":2,"minecraft:honeycomb_block":26,"minecraft:green_terracotta":10,"minecraft:lime_carpet":1,"minecraft:honey_bottle":9,"minecraft:horn_coral_fan":7,"minecraft:polished_basalt":549,"minecraft:carved_pumpkin":14,"minecraft:red_tulip":29,"minecraft:glowstone":4,"minecraft:bookshelf":12,"minecraft:end_rod":206,"minecraft:white_terracotta":164,"minecraft:iron_bars":37,"minecraft:snowball":575,"minecraft:sponge":14,"minecraft:feather":31,"minecraft:cooked_beef":115,"minecraft:water_bucket":5,"minecraft:flint":22,"minecraft:lantern":66,"minecraft:purple_carpet":148,"minecraft:stonecutter":16,"minecraft:dark_oak_sign":3,"minecraft:diamond_helmet":7,"minecraft:honeycomb":27,"minecraft:lime_terracotta":129,"minecraft:birch_fence_gate":14,"minecraft:stripped_spruce_log":166,"minecraft:brown_mushroom_block":7,"minecraft:iron_hoe":3,"minecraft:polished_andesite":31,"minecraft:blue_terracotta":1948,"minecraft:deepslate":1233,"minecraft:lever":12,"minecraft:granite":23,"minecraft:spruce_button":4,"minecraft:rooted_dirt":59,"minecraft:deepslate_coal_ore":31,"minecraft:light_gray_carpet":2,"minecraft:crimson_roots":8,"minecraft:diamond_pickaxe":9,"minecraft:mud":9,"minecraft:bee_nest":13,"minecraft:clay_ball":1436,"minecraft:redstone_lamp":1,"minecraft:cornflower":113,"minecraft:elytra":4,"minecraft:white_carpet":55,"minecraft:iron_shovel":2,"minecraft:glass_pane":19,"minecraft:netherite_sword":5,"minecraft:jungle_sapling":15,"minecraft:poppy":108,"minecraft:spruce_slab":344,"minecraft:birch_sapling":41,"minecraft:piston":9,"minecraft:copper_ore":50,"minecraft:lime_shulker_box":33,"minecraft:black_stained_glass":16,"minecraft:stone":8014,"minecraft:fire_charge":15,"minecraft:white_dye":3,"minecraft:netherite_pickaxe":6,"minecraft:diamond_chestplate":4,"minecraft:hay_block":330,"minecraft:yellow_terracotta":2,"minecraft:totem_of_undying":9,"minecraft:mutton":17,"minecraft:bone_block":168,"minecraft:emerald_ore":3,"minecraft:yellow_shulker_box":2,"minecraft:mud_bricks":28,"minecraft:clock":1,"minecraft:acacia_wood":47,"minecraft:packed_mud":199,"minecraft:lily_pad":3,"minecraft:paper":64,"minecraft:apple":25,"minecraft:iron_ore":61,"minecraft:gray_bed":2,"minecraft:dark_oak_stairs":13,"minecraft:smooth_basalt":268,"minecraft:sweet_berries":76,"minecraft:crimson_stairs":2,"minecraft:crying_obsidian":1,"minecraft:leather_helmet":3,"minecraft:coal_ore":156,"minecraft:slime_ball":4,"minecraft:deepslate_redstone_ore":28,"minecraft:painting":21,"minecraft:birch_sign":7,"minecraft:polished_blackstone_brick_wall":292,"minecraft:baked_potato":1,"minecraft:hopper":45,"minecraft:light_blue_concrete":2,"minecraft:ender_chest":8,"minecraft:nether_brick_fence":4,"minecraft:stone_brick_stairs":187,"minecraft:dead_tube_coral_block":1,"minecraft:waxed_cut_copper_slab":7,"minecraft:deepslate_lapis_ore":2,"minecraft:red_sand":8,"minecraft:smooth_stone":41,"minecraft:comparator":10,"minecraft:bucket":5,"minecraft:white_tulip":25,"minecraft:rose_bush":20,"minecraft:cobblestone_slab":54,"minecraft:ender_eye":934,"minecraft:azalea":31,"minecraft:wooden_shovel":12,"minecraft:deepslate_iron_ore":11,"minecraft:tipped_arrow":56,"minecraft:birch_trapdoor":23,"minecraft:polished_deepslate_stairs":79,"minecraft:spruce_stairs":285,"minecraft:vine":1,"minecraft:andesite_wall":23,"minecraft:rotten_flesh":286,"minecraft:music_disc_ward":1,"minecraft:brown_shulker_box":24,"minecraft:mangrove_roots":1954,"minecraft:chorus_flower":1,"minecraft:obsidian":308,"minecraft:cobblestone":1389,"minecraft:leather_chestplate":1,"minecraft:lilac":2,"minecraft:andesite":900,"minecraft:golden_leggings":4,"minecraft:mud_brick_stairs":10,"minecraft:beacon":3,"minecraft:potato":720,"minecraft:prismarine_bricks":2,"minecraft:dirt":4001,"minecraft:glass":331,"minecraft:bone":407,"minecraft:acacia_planks":2,"minecraft:bow":31,"minecraft:wheat_seeds":5371,"minecraft:orange_tulip":19,"minecraft:birch_wood":11,"minecraft:netherite_axe":3,"minecraft:mossy_stone_bricks":41,"minecraft:bamboo":2467,"minecraft:gray_stained_glass":30,"minecraft:black_stained_glass_pane":6,"minecraft:light_blue_shulker_box":41,"minecraft:nether_brick_stairs":1,"minecraft:grass_block":113,"minecraft:jungle_slab":70,"minecraft:spectral_arrow":2,"minecraft:mossy_cobblestone":37,"minecraft:light_gray_terracotta":175,"minecraft:sugar":5,"minecraft:light_blue_terracotta":1861,"minecraft:netherite_helmet":3,"minecraft:slime_block":6,"minecraft:soul_lantern":2,"minecraft:cracked_polished_blackstone_bricks":3,"minecraft:crossbow":16,"minecraft:bone_meal":381,"minecraft:golden_apple":3,"minecraft:spruce_sign":14,"minecraft:emerald":55,"minecraft:netherrack":913,"minecraft:andesite_slab":369,"minecraft:oak_leaves":34,"minecraft:azure_bluet":447,"minecraft:ladder":93,"minecraft:packed_ice":74,"minecraft:brown_mushroom":14,"minecraft:stone_brick_wall":189,"minecraft:chain":60,"minecraft:shield":5,"minecraft:oak_trapdoor":7,"minecraft:moss_carpet":464,"minecraft:birch_fence":12,"minecraft:blackstone":101,"minecraft:creeper_banner_pattern":1,"minecraft:end_stone":1,"minecraft:flowering_azalea_leaves":25,"minecraft:polished_blackstone_bricks":9,"minecraft:cookie":3,"minecraft:trident":3,"minecraft:light_gray_stained_glass_pane":4,"minecraft:purple_terracotta":581,"minecraft:weeping_vines":18,"minecraft:red_shulker_box":109,"minecraft:pumpkin_pie":8,"minecraft:nether_bricks":293,"minecraft:pink_tulip":4,"minecraft:black_banner":51,"minecraft:skeleton_skull":14,"minecraft:netherite_boots":4,"minecraft:basalt":232,"minecraft:leather":174,"minecraft:yellow_bed":21,"minecraft:gunpowder":4604,"minecraft:cooked_mutton":16,"minecraft:red_carpet":11,"minecraft:gray_carpet":11,"minecraft:deepslate_emerald_ore":1,"minecraft:spruce_wood":62,"minecraft:iron_ingot":70,"minecraft:cooked_chicken":18,"minecraft:polished_andesite_slab":6,"minecraft:sculk_catalyst":2,"minecraft:tropical_fish_bucket":5,"minecraft:black_candle":8,"minecraft:stone_brick_slab":34,"minecraft:quartz":383,"minecraft:dandelion":200,"minecraft:lava_bucket":4,"minecraft:amethyst_shard":141,"minecraft:spruce_door":37,"minecraft:brick_slab":4,"minecraft:polished_diorite_stairs":77,"minecraft:sculk_sensor":12,"minecraft:chainmail_leggings":2,"minecraft:terracotta":436,"minecraft:damaged_anvil":1,"minecraft:netherite_hoe":2,"minecraft:dark_oak_wood":73,"minecraft:sunflower":11,"minecraft:birch_door":1,"minecraft:iron_chestplate":1,"minecraft:chainmail_boots":2,"minecraft:flower_pot":7,"minecraft:anvil":6,"minecraft:prismarine_shard":5,"minecraft:diamond_sword":5,"minecraft:oak_stairs":12,"minecraft:wither_rose":3,"minecraft:golden_shovel":1,"minecraft:golden_sword":1,"minecraft:polished_deepslate_wall":16,"minecraft:amethyst_block":32,"minecraft:dark_oak_trapdoor":2,"minecraft:soul_soil":90,"minecraft:beetroot":246,"minecraft:gold_nugget":8,"minecraft:cobbled_deepslate":9218,"minecraft:spruce_planks":521,"minecraft:flower_banner_pattern":1,"minecraft:written_book":3,"minecraft:azalea_leaves":18,"minecraft:melon_slice":69,"minecraft:mangrove_log":764,"minecraft:golden_helmet":1,"minecraft:beehive":8,"minecraft:composter":4,"minecraft:green_bed":2,"minecraft:sandstone_wall":7,"minecraft:deepslate_tile_stairs":29,"minecraft:black_dye":193,"minecraft:waxed_cut_copper_stairs":3,"minecraft:tropical_fish":14,"minecraft:blue_dye":1,"minecraft:iron_block":815,"minecraft:cyan_terracotta":2552,"minecraft:netherite_chestplate":6,"minecraft:birch_log":196,"minecraft:magma_block":2,"minecraft:polished_diorite_slab":2,"minecraft:iron_door":2,"minecraft:birch_slab":66,"minecraft:jungle_log":239,"minecraft:netherite_leggings":7,"minecraft:map":25,"minecraft:mangrove_slab":33,"minecraft:chipped_anvil":4,"minecraft:glowstone_dust":43,"minecraft:moss_block":137,"minecraft:ink_sac":163,"minecraft:crimson_door":2,"minecraft:loom":2,"minecraft:barrel":11,"minecraft:trapped_chest":11,"minecraft:dark_oak_log":515,"minecraft:dispenser":8,"minecraft:deepslate_gold_ore":6,"minecraft:dead_brain_coral_block":2,"minecraft:blue_ice":13,"minecraft:bread":81,"minecraft:dark_oak_fence":99,"minecraft:bricks":8,"minecraft:spruce_leaves":41,"minecraft:crafting_table":95,"minecraft:coarse_dirt":150,"minecraft:bubble_coral_fan":5,"minecraft:orange_banner":4,"minecraft:crimson_trapdoor":35,"minecraft:dead_horn_coral_block":1,"minecraft:red_bed":28,"minecraft:netherite_scrap":17,"minecraft:compass":2,"minecraft:cracked_stone_bricks":66,"minecraft:deepslate_diamond_ore":50,"minecraft:beef":78,"minecraft:quartz_stairs":59,"minecraft:chest":44,"minecraft:egg":156,"minecraft:sandstone":87,"minecraft:polished_deepslate_slab":173,"minecraft:glow_item_frame":1,"minecraft:amethyst_cluster":30,"minecraft:spruce_fence":150,"minecraft:carrot":1709,"minecraft:redstone":630,"minecraft:prismarine_crystals":14,"minecraft:tnt":29,"minecraft:cooked_cod":21,"minecraft:beetroot_seeds":670,"minecraft:tube_coral_fan":6,"minecraft:shears":1,"minecraft:diamond_boots":6,"minecraft:tube_coral_block":5,"minecraft:gold_ingot":115,"minecraft:white_shulker_box":12,"minecraft:glow_berries":14,"minecraft:crimson_slab":43,"minecraft:white_wool":274,"minecraft:lapis_ore":2,"minecraft:stripped_oak_log":26,"minecraft:red_mushroom":10,"minecraft:filled_map":173,"minecraft:oak_log":1708,"minecraft:ancient_debris":7,"minecraft:golden_boots":5,"minecraft:white_banner":13,"minecraft:stone_bricks":718,"minecraft:kelp":476,"minecraft:glass_bottle":7,"minecraft:mangrove_planks":49,"minecraft:flowering_azalea":18,"minecraft:dark_oak_slab":51,"minecraft:white_stained_glass_pane":23,"minecraft:daylight_detector":1,"minecraft:gravel":308,"minecraft:birch_stairs":9,"minecraft:spruce_sapling":394,"minecraft:spruce_log":4787,"minecraft:sea_lantern":86,"minecraft:firework_rocket":572,"minecraft:purple_bed":13,"minecraft:polished_diorite":1,"minecraft:diamond_axe":9,"minecraft:gray_wool":1,"minecraft:oak_button":4,"minecraft:crimson_nylium":5,"minecraft:mangrove_propagule":258,"minecraft:ender_pearl":705,"minecraft:music_disc_strad":1,"minecraft:wheat":1937,"minecraft:potion":3,"minecraft:brain_coral_block":21,"minecraft:crimson_planks":3,"minecraft:raw_copper":511,"minecraft:smooth_stone_slab":151,"minecraft:iron_leggings":6,"minecraft:sticky_piston":3,"minecraft:netherite_ingot":5,"minecraft:zombie_head":4,"minecraft:oak_sign":1,"minecraft:sea_pickle":35,"minecraft:deepslate_tiles":5,"minecraft:black_shulker_box":61,"minecraft:calcite":487,"minecraft:furnace":22,"minecraft:iron_boots":3,"minecraft:stick":790,"minecraft:orange_shulker_box":5,"minecraft:oak_fence":17,"minecraft:torch":382,"minecraft:porkchop":7,"minecraft:snow_block":14,"minecraft:dried_kelp":59,"minecraft:target":1,"minecraft:pointed_dripstone":4,"minecraft:quartz_block":8,"minecraft:mangrove_stairs":167,"minecraft:fire_coral_fan":1,"minecraft:cod":18,"minecraft:magenta_dye":1,"minecraft:tuff":686,"minecraft:wither_skeleton_skull":1,"minecraft:green_shulker_box":19,"minecraft:lapis_lazuli":130,"minecraft:leather_boots":2,"minecraft:raw_gold":1,"minecraft:cobbled_deepslate_slab":61,"minecraft:bell":3,"minecraft:light_blue_dye":1,"minecraft:oak_planks":11,"minecraft:mossy_stone_brick_stairs":1,"minecraft:cooked_porkchop":87,"minecraft:axolotl_bucket":5,"minecraft:oak_pressure_plate":2,"minecraft:poisonous_potato":4,"minecraft:jungle_planks":7,"minecraft:sand":2747,"minecraft:shulker_box":50,"minecraft:dark_prismarine":2,"minecraft:spruce_fence_gate":29,"minecraft:clay":3,"minecraft:diamond":44,"minecraft:spruce_boat":69,"minecraft:oak_sapling":171,"minecraft:bubble_coral_block":3,"minecraft:nether_star":2,"minecraft:cocoa_beans":677,"minecraft:allium":100,"minecraft:chicken":6,"minecraft:gold_block":39,"minecraft:stone_stairs":16,"minecraft:item_frame":28,"minecraft:quartz_slab":8,"minecraft:candle":66,"minecraft:mossy_cobblestone_wall":3,"minecraft:andesite_stairs":52,"minecraft:player_head":37,"minecraft:observer":22,"minecraft:light_gray_wool":1,"minecraft:tinted_glass":3,"minecraft:blue_shulker_box":30,"minecraft:sugar_cane":3183,"minecraft:spruce_trapdoor":726,"minecraft:dark_oak_sapling":118,"minecraft:raw_iron":138,"minecraft:copper_ingot":7,"minecraft:red_stained_glass_pane":27,"minecraft:bowl":1,"minecraft:quartz_pillar":9,"minecraft:stone_button":73,"minecraft:dark_oak_planks":21,"minecraft:arrow":346,"minecraft:golden_hoe":1,"minecraft:saddle":2,"minecraft:wet_sponge":16,"minecraft:glow_ink_sac":14,"minecraft:crimson_stem":162,"minecraft:salmon":48,"minecraft:birch_planks":20,"minecraft:nether_wart_block":43,"minecraft:cobblestone_stairs":90,"minecraft:deepslate_tile_slab":14,"minecraft:fire_coral_block":9,"minecraft:mossy_stone_brick_wall":1,"minecraft:acacia_sapling":19,"minecraft:soul_sand":267,"minecraft:oak_slab":54,"minecraft:book":1,"minecraft:scaffolding":190,"minecraft:pumpkin":17,"minecraft:chiseled_stone_bricks":2,"minecraft:brain_coral_fan":2,"minecraft:mud_brick_wall":1,"minecraft:blast_furnace":4,"minecraft:white_bed":19,"minecraft:gold_ore":6,"minecraft:dark_oak_fence_gate":42,"minecraft:mossy_stone_brick_slab":2,"minecraft:spider_eye":21,"minecraft:stripped_jungle_log":3,"minecraft:lime_dye":3,"minecraft:campfire":5,"minecraft:honey_block":11,"minecraft:dead_bubble_coral_block":1,"minecraft:iron_helmet":5,"minecraft:acacia_slab":4,"minecraft:black_wool":31,"minecraft:coal":299},"minecraft:crafted":{"minecraft:red_stained_glass_pane":32,"minecraft:black_dye":93,"minecraft:waxed_cut_copper_slab":40,"minecraft:polished_deepslate_wall":10,"minecraft:chain":9,"minecraft:diamond_shovel":1,"minecraft:iron_door":3,"minecraft:waxed_cut_copper_stairs":40,"minecraft:black_wool":60,"minecraft:gray_stained_glass":936,"minecraft:smithing_table":1,"minecraft:sticky_piston":1,"minecraft:polished_deepslate_slab":264,"minecraft:painting":1,"minecraft:stone_brick_stairs":259,"minecraft:stone_slab":138,"minecraft:iron_pickaxe":5,"minecraft:sandstone":4,"minecraft:netherite_ingot":2,"minecraft:composter":10,"minecraft:polished_blackstone_bricks":14,"minecraft:golden_carrot":37,"minecraft:iron_nugget":333,"minecraft:crimson_trapdoor":24,"minecraft:diamond_hoe":1,"minecraft:soul_torch":4,"minecraft:blue_shulker_box":2,"minecraft:spruce_fence":87,"minecraft:stone_stairs":22,"minecraft:lantern":32,"minecraft:spruce_stairs":536,"minecraft:red_shulker_box":2,"minecraft:stone_pickaxe":2,"minecraft:quartz_slab":6,"minecraft:spruce_boat":42,"minecraft:purple_carpet":66,"minecraft:brick_slab":38,"minecraft:cut_copper_slab":40,"minecraft:crimson_slab":54,"minecraft:polished_blackstone_stairs":4,"minecraft:dark_oak_button":2,"minecraft:red_carpet":6,"minecraft:deepslate_tiles":27,"minecraft:crimson_stairs":12,"minecraft:oak_fence_gate":66,"minecraft:red_stained_glass":16,"minecraft:soul_lantern":4,"minecraft:birch_trapdoor":96,"minecraft:black_stained_glass_pane":16,"minecraft:iron_shovel":4,"minecraft:mangrove_slab":432,"minecraft:grindstone":1,"minecraft:cobblestone_slab":460,"minecraft:barrel":10,"minecraft:birch_wood":66,"minecraft:crimson_sign":3,"minecraft:stone":2,"minecraft:stone_brick_slab":182,"minecraft:mangrove_fence":3,"minecraft:bow":1,"minecraft:comparator":5,"minecraft:chest":286,"minecraft:netherite_helmet":2,"minecraft:oak_button":33,"minecraft:copper_block":21,"minecraft:bricks":80,"minecraft:oak_fence":69,"minecraft:stone_bricks":1110,"minecraft:white_banner":2,"minecraft:mud_brick_stairs":19,"minecraft:cauldron":4,"minecraft:iron_helmet":1,"minecraft:brown_dye":1,"minecraft:red_wool":4,"minecraft:chiseled_polished_blackstone":2,"minecraft:white_stained_glass_pane":64,"minecraft:dispenser":6,"minecraft:tnt":17,"minecraft:spruce_trapdoor":610,"minecraft:yellow_dye":2,"minecraft:purple_dye":146,"minecraft:stick":1252,"minecraft:iron_ingot":1531,"minecraft:andesite_stairs":40,"minecraft:light_blue_shulker_box":2,"minecraft:dark_oak_fence_gate":66,"minecraft:deepslate_tile_slab":16,"minecraft:orange_glazed_terracotta":1,"minecraft:tripwire_hook":6,"minecraft:stone_brick_wall":472,"minecraft:fishing_rod":1,"minecraft:beehive":4,"minecraft:netherite_sword":1,"minecraft:spruce_button":1,"minecraft:mossy_stone_bricks":42,"minecraft:mud_bricks":176,"minecraft:blast_furnace":3,"minecraft:furnace":21,"minecraft:piston":134,"minecraft:oak_trapdoor":28,"minecraft:flint_and_steel":2,"minecraft:scaffolding":1632,"minecraft:netherite_chestplate":1,"minecraft:cobblestone_wall":1,"minecraft:brown_shulker_box":1,"minecraft:mangrove_pressure_plate":8,"minecraft:honey_block":9,"minecraft:purple_stained_glass":16,"minecraft:iron_sword":1,"minecraft:black_banner":10,"minecraft:mangrove_planks":1212,"minecraft:jungle_planks":344,"minecraft:white_dye":168,"minecraft:netherite_shovel":1,"minecraft:crimson_door":3,"minecraft:stonecutter":2,"minecraft:anvil":4,"minecraft:torch":236,"minecraft:ender_chest":4,"minecraft:smooth_stone":190,"minecraft:purple_bed":1,"minecraft:dark_oak_wood":288,"minecraft:birch_slab":570,"minecraft:loom":1,"minecraft:lever":16,"minecraft:iron_bars":256,"minecraft:quartz_block":32,"minecraft:glass":2308,"minecraft:netherite_boots":2,"minecraft:birch_fence_gate":12,"minecraft:mangrove_stairs":600,"minecraft:polished_blackstone":24,"minecraft:birch_door":3,"minecraft:magenta_dye":3,"minecraft:glass_bottle":60,"minecraft:wooden_shovel":13,"minecraft:spruce_door":24,"minecraft:copper_ingot":453,"minecraft:hay_block":111,"minecraft:campfire":12,"minecraft:lime_shulker_box":1,"minecraft:compass":39,"minecraft:iron_block":16,"minecraft:gold_ingot":2,"minecraft:spruce_fence_gate":20,"minecraft:birch_stairs":16,"minecraft:stone_shovel":7,"minecraft:smooth_stone_slab":342,"minecraft:polished_deepslate_stairs":160,"minecraft:cut_copper_stairs":64,"minecraft:yellow_bed":1,"minecraft:bone_meal":1230,"minecraft:andesite_wall":147,"minecraft:candle":57,"minecraft:white_carpet":24,"minecraft:dark_oak_fence":18,"minecraft:ladder":51,"minecraft:spruce_slab":2388,"minecraft:redstone_block":1,"minecraft:dark_oak_planks":740,"minecraft:wheat":189,"minecraft:daylight_detector":1,"minecraft:polished_blackstone_brick_slab":22,"minecraft:red_bed":1,"minecraft:glowstone":8,"minecraft:white_stained_glass":24,"minecraft:jungle_slab":426,"minecraft:sandstone_wall":4,"minecraft:mossy_stone_brick_stairs":1,"minecraft:andesite_slab":70,"minecraft:oak_stairs":16,"minecraft:deepslate_tile_stairs":43,"minecraft:iron_leggings":2,"minecraft:white_bed":10,"minecraft:nether_brick_stairs":8,"minecraft:brick":321,"minecraft:oak_planks":724,"minecraft:dark_oak_boat":1,"minecraft:mossy_stone_brick_slab":2,"minecraft:cobblestone_stairs":144,"minecraft:spruce_pressure_plate":10,"minecraft:hopper":187,"minecraft:iron_boots":1,"minecraft:stone_hoe":4,"minecraft:quartz_stairs":8,"minecraft:item_frame":27,"minecraft:oak_slab":114,"minecraft:map":33,"minecraft:crafting_table":14,"minecraft:spruce_planks":7268,"minecraft:gold_block":8,"minecraft:birch_planks":656,"minecraft:sea_pickle":1,"minecraft:black_shulker_box":1,"minecraft:dark_oak_slab":108,"minecraft:shield":3,"minecraft:iron_chestplate":1,"minecraft:paper":3138,"minecraft:diamond_pickaxe":1,"minecraft:charcoal":18,"minecraft:birch_fence":48,"minecraft:light_blue_dye":2,"minecraft:netherite_hoe":1,"minecraft:snow_block":14,"minecraft:polished_blackstone_brick_stairs":3,"minecraft:redstone_torch":15,"minecraft:shears":8,"minecraft:light_gray_stained_glass_pane":8,"minecraft:polished_andesite":68,"minecraft:coarse_dirt":48,"minecraft:purple_wool":44,"minecraft:cobbled_deepslate_slab":58,"minecraft:redstone":63,"minecraft:popped_chorus_fruit":18,"minecraft:stone_button":94,"minecraft:dark_oak_trapdoor":6,"minecraft:gray_dye":162,"minecraft:mossy_stone_brick_wall":1,"minecraft:diamond_block":7,"minecraft:glass_pane":16,"minecraft:blue_ice":4,"minecraft:netherite_leggings":4,"minecraft:polished_deepslate":963,"minecraft:spruce_wood":75,"minecraft:iron_axe":10,"minecraft:iron_hoe":1,"minecraft:slime_ball":9,"minecraft:lime_dye":1,"minecraft:observer":198,"minecraft:cooked_beef":61,"minecraft:sugar":26,"minecraft:red_dye":80,"minecraft:cooked_cod":38,"minecraft:bone_block":30,"minecraft:crimson_planks":208,"minecraft:diamond_sword":1,"minecraft:spruce_sign":21,"minecraft:dark_oak_stairs":12,"minecraft:bucket":6,"minecraft:stone_axe":7,"minecraft:amethyst_block":34,"minecraft:bread":65,"minecraft:black_stained_glass":8,"minecraft:blue_dye":106,"minecraft:mud_brick_wall":82,"minecraft:oak_boat":1,"minecraft:white_wool":47,"minecraft:gold_nugget":315,"minecraft:acacia_planks":20,"minecraft:clay":162,"minecraft:trapped_chest":6,"minecraft:firework_rocket":6498},"minecraft:custom":{"minecraft:interact_with_crafting_table":920,"minecraft:damage_blocked_by_shield":70507,"minecraft:play_time":14068124,"minecraft:deaths":397,"minecraft:jump":68057,"minecraft:play_record":5,"minecraft:interact_with_smoker":20,"minecraft:inspect_dispenser":66,"minecraft:horse_one_cm":67729,"minecraft:interact_with_anvil":110,"minecraft:inspect_hopper":97,"minecraft:time_since_rest":7591,"minecraft:swim_one_cm":2107681,"minecraft:open_chest":4186,"minecraft:open_shulker_box":2835,"minecraft:damage_resisted":6212,"minecraft:talked_to_villager":28,"minecraft:interact_with_brewingstand":6,"minecraft:interact_with_beacon":20,"minecraft:fill_cauldron":1,"minecraft:interact_with_campfire":9,"minecraft:damage_dealt_resisted":115,"minecraft:boat_one_cm":30560,"minecraft:damage_taken":188852,"minecraft:aviate_one_cm":68359510,"minecraft:open_barrel":153,"minecraft:bell_ring":13,"minecraft:eat_cake_slice":105,"minecraft:leave_game":253,"minecraft:time_since_death":628279,"minecraft:enchant_item":2,"minecraft:interact_with_furnace":550,"minecraft:traded_with_villager":1,"minecraft:sleep_in_bed":711,"minecraft:damage_dealt":184153,"minecraft:use_cauldron":8,"minecraft:interact_with_smithing_table":16,"minecraft:sneak_time":1274961,"minecraft:interact_with_blast_furnace":69,"minecraft:total_world_time":14068124,"minecraft:interact_with_stonecutter":134,"minecraft:fly_one_cm":7576097,"minecraft:fish_caught":45,"minecraft:fall_one_cm":3035965,"minecraft:animals_bred":202,"minecraft:sprint_one_cm":19467638,"minecraft:drop":2441,"minecraft:walk_on_water_one_cm":1781362,"minecraft:interact_with_loom":43,"minecraft:open_enderchest":490,"minecraft:player_kills":13,"minecraft:crouch_one_cm":2599485,"minecraft:mob_kills":4613,"minecraft:climb_one_cm":396707,"minecraft:walk_one_cm":37772345,"minecraft:walk_under_water_one_cm":3156887,"minecraft:interact_with_grindstone":4,"minecraft:damage_absorbed":651,"minecraft:trigger_trapped_chest":115},"minecraft:mined":{"minecraft:red_shulker_box":109,"minecraft:white_bed":19,"minecraft:fire_coral_wall_fan":1,"minecraft:granite":21,"minecraft:oak_pressure_plate":1,"minecraft:oak_wall_sign":1,"minecraft:red_stained_glass_pane":30,"minecraft:spawner":7,"minecraft:polished_blackstone_bricks":9,"minecraft:magma_block":7,"minecraft:dark_oak_trapdoor":2,"minecraft:fire":19,"minecraft:barrel":11,"minecraft:cobbled_deepslate":448,"minecraft:deepslate_lapis_ore":6,"minecraft:nether_brick_stairs":1,"minecraft:potted_dandelion":3,"minecraft:spruce_pressure_plate":1,"minecraft:pink_tulip":4,"minecraft:white_shulker_box":10,"minecraft:spruce_wood":56,"minecraft:white_banner":1,"minecraft:player_head":9,"minecraft:tripwire":3,"minecraft:kelp_plant":80,"minecraft:crimson_nylium":10,"minecraft:deepslate_tile_slab":14,"minecraft:powder_snow":11,"minecraft:torch":127,"minecraft:dark_oak_wood":103,"minecraft:melon":14,"minecraft:white_stained_glass_pane":36,"minecraft:dead_bush":12,"minecraft:spruce_wall_sign":5,"minecraft:lime_shulker_box":33,"minecraft:sugar_cane":1467,"minecraft:bricks":8,"minecraft:amethyst_block":26,"minecraft:birch_sapling":6,"minecraft:white_terracotta":229,"minecraft:chain":71,"minecraft:mud":12,"minecraft:tinted_glass":3,"minecraft:jukebox":4,"minecraft:wither_rose":1,"minecraft:grass":636,"minecraft:dark_oak_sapling":3,"minecraft:sandstone_wall":7,"minecraft:mangrove_log":12,"minecraft:smooth_basalt":272,"minecraft:deepslate":6601,"minecraft:deepslate_tiles":5,"minecraft:dark_prismarine":3,"minecraft:mossy_cobblestone":21,"minecraft:dark_oak_log":233,"minecraft:sea_lantern":91,"minecraft:birch_fence_gate":14,"minecraft:dark_oak_fence":79,"minecraft:spruce_fence":69,"minecraft:redstone_wire":17,"minecraft:red_mushroom":3,"minecraft:packed_mud":201,"minecraft:green_terracotta":10,"minecraft:andesite":691,"minecraft:mossy_stone_brick_stairs":1,"minecraft:cobblestone_slab":43,"minecraft:vine":103,"minecraft:brain_coral_wall_fan":2,"minecraft:bone_block":168,"minecraft:fire_coral_block":10,"minecraft:ender_chest":8,"minecraft:oak_slab":45,"minecraft:birch_stairs":9,"minecraft:glass_pane":41,"minecraft:soul_sand":270,"minecraft:polished_blackstone_brick_wall":47,"minecraft:dandelion":53,"minecraft:cornflower":115,"minecraft:crimson_slab":33,"minecraft:campfire":6,"minecraft:tall_grass":127,"minecraft:copper_ore":108,"minecraft:deepslate_gold_ore":10,"minecraft:black_stained_glass":12,"minecraft:coarse_dirt":57,"minecraft:trapped_chest":10,"minecraft:mangrove_leaves":84,"minecraft:sunflower":11,"minecraft:gravel":250,"minecraft:cobweb":4,"minecraft:oak_button":2,"minecraft:birch_sign":5,"minecraft:stone_bricks":717,"minecraft:chipped_anvil":4,"minecraft:gold_ore":7,"minecraft:fern":14,"minecraft:oak_sapling":34,"minecraft:farmland":71,"minecraft:mossy_stone_brick_slab":2,"minecraft:andesite_stairs":26,"minecraft:orange_stained_glass":3,"minecraft:spruce_trapdoor":140,"minecraft:cracked_polished_blackstone_bricks":3,"minecraft:polished_diorite":1,"minecraft:polished_blackstone_brick_slab":34,"minecraft:composter":3,"minecraft:sculk_catalyst":2,"minecraft:red_tulip":18,"minecraft:skeleton_wall_skull":4,"minecraft:flowering_azalea_leaves":27,"minecraft:iron_bars":36,"minecraft:azalea":26,"minecraft:spruce_slab":298,"minecraft:waxed_cut_copper_stairs":3,"minecraft:deepslate_redstone_ore":39,"minecraft:brown_shulker_box":24,"minecraft:quartz_block":9,"minecraft:light_gray_terracotta":228,"minecraft:mossy_cobblestone_wall":4,"minecraft:beacon":1,"minecraft:nether_quartz_ore":33,"minecraft:oak_planks":3,"minecraft:wall_torch":84,"minecraft:stone_stairs":15,"minecraft:light_blue_terracotta":1986,"minecraft:blue_terracotta":2049,"minecraft:dark_oak_slab":47,"minecraft:mossy_stone_brick_wall":1,"minecraft:blue_ice":5,"minecraft:tnt":21,"minecraft:smooth_stone_slab":159,"minecraft:oak_log":377,"minecraft:beetroots":259,"minecraft:lime_terracotta":155,"minecraft:dirt":1786,"minecraft:dispenser":8,"minecraft:ancient_debris":8,"minecraft:daylight_detector":1,"minecraft:crying_obsidian":1,"minecraft:quartz_stairs":58,"minecraft:dark_oak_leaves":76,"minecraft:mangrove_roots":239,"minecraft:glow_lichen":8,"minecraft:lever":9,"minecraft:ladder":77,"minecraft:purple_terracotta":571,"minecraft:tube_coral_wall_fan":6,"minecraft:stone_button":4,"minecraft:brown_mushroom_block":9,"minecraft:birch_slab":70,"minecraft:spruce_leaves":182,"minecraft:acacia_slab":4,"minecraft:crimson_stem":76,"minecraft:hay_block":116,"minecraft:polished_basalt":556,"minecraft:gold_block":30,"minecraft:nether_brick_fence":4,"minecraft:bookshelf":12,"minecraft:deepslate_iron_ore":21,"minecraft:shroomlight":26,"minecraft:stripped_oak_log":19,"minecraft:wet_sponge":1,"minecraft:acacia_leaves":3,"minecraft:scaffolding":106,"minecraft:basalt":262,"minecraft:oak_fence":16,"minecraft:honey_block":13,"minecraft:gray_stained_glass":42,"minecraft:stone_slab":54,"minecraft:deepslate_coal_ore":22,"minecraft:polished_blackstone_brick_stairs":1,"minecraft:prismarine_bricks":1,"minecraft:birch_planks":20,"minecraft:sea_pickle":21,"minecraft:ice":101,"minecraft:black_wall_banner":32,"minecraft:mangrove_planks":26,"minecraft:white_wall_banner":3,"minecraft:bee_nest":20,"minecraft:cocoa":218,"minecraft:purple_shulker_box":7,"minecraft:cracked_stone_bricks":26,"minecraft:small_dripleaf":3,"minecraft:mossy_stone_bricks":47,"minecraft:dark_oak_planks":87,"minecraft:light_blue_concrete":2,"minecraft:jungle_leaves":22,"minecraft:carved_pumpkin":8,"minecraft:obsidian":248,"minecraft:red_sand":8,"minecraft:crimson_trapdoor":35,"minecraft:stone_brick_wall":192,"minecraft:jungle_log":128,"minecraft:deepslate_tile_stairs":31,"minecraft:bubble_coral_block":3,"minecraft:tube_coral_block":6,"minecraft:hopper":41,"minecraft:chiseled_stone_bricks":2,"minecraft:weeping_vines_plant":8,"minecraft:tall_seagrass":43,"minecraft:sticky_piston":3,"minecraft:pumpkin":20,"minecraft:moss_carpet":47,"minecraft:sculk_shrieker":8,"minecraft:cave_vines":2,"minecraft:polished_deepslate_slab":164,"minecraft:dirt_path":223,"minecraft:oak_stairs":12,"minecraft:quartz_slab":7,"minecraft:iron_block":346,"minecraft:conduit":1,"minecraft:brown_mushroom":4,"minecraft:red_bed":27,"minecraft:player_wall_head":23,"minecraft:soul_fire":6,"minecraft:amethyst_cluster":39,"minecraft:blast_furnace":4,"minecraft:mud_brick_stairs":10,"minecraft:polished_diorite_slab":2,"minecraft:glass":346,"minecraft:damaged_anvil":1,"minecraft:crimson_stairs":2,"minecraft:spruce_sign":4,"minecraft:skeleton_skull":2,"minecraft:polished_diorite_stairs":83,"minecraft:wheat":1689,"minecraft:lilac":2,"minecraft:birch_door":1,"minecraft:potted_poppy":4,"minecraft:stone_brick_stairs":184,"minecraft:loom":2,"minecraft:zombie_wall_head":1,"minecraft:blue_shulker_box":30,"minecraft:red_mushroom_block":1,"minecraft:stonecutter":16,"minecraft:piston":4,"minecraft:yellow_terracotta":4,"minecraft:light_gray_stained_glass_pane":6,"minecraft:shulker_box":37,"minecraft:nether_bricks":176,"minecraft:cobbled_deepslate_slab":70,"minecraft:allium":59,"minecraft:jungle_planks":7,"minecraft:crimson_roots":8,"minecraft:orange_shulker_box":5,"minecraft:moss_block":148,"minecraft:kelp":79,"minecraft:horn_coral_wall_fan":7,"minecraft:black_stained_glass_pane":11,"minecraft:jungle_sapling":10,"minecraft:snow":405,"minecraft:acacia_wood":1,"minecraft:potatoes":253,"minecraft:bamboo_sapling":4,"minecraft:bamboo":234,"minecraft:white_wool":12,"minecraft:cake":2,"minecraft:light_gray_carpet":2,"minecraft:mangrove_stairs":174,"minecraft:comparator":9,"minecraft:brown_stained_glass_pane":4,"minecraft:stone_brick_slab":28,"minecraft:observer":24,"minecraft:spruce_button":4,"minecraft:emerald_ore":3,"minecraft:sponge":14,"minecraft:purple_bed":10,"minecraft:white_carpet":45,"minecraft:spruce_log":1452,"minecraft:birch_leaves":134,"minecraft:quartz_pillar":9,"minecraft:dark_oak_sign":3,"minecraft:zombie_head":2,"minecraft:acacia_planks":15,"minecraft:spruce_fence_gate":33,"minecraft:deepslate_emerald_ore":1,"minecraft:black_shulker_box":60,"minecraft:waxed_cut_copper_slab":6,"minecraft:spruce_planks":457,"minecraft:cobblestone_stairs":90,"minecraft:sculk_vein":1,"minecraft:grass_block":1690,"minecraft:dead_tube_coral_block":1,"minecraft:soul_soil":100,"minecraft:mud_bricks":28,"minecraft:mud_brick_wall":1,"minecraft:smooth_stone":52,"minecraft:glowstone":4,"minecraft:iron_ore":105,"minecraft:target":1,"minecraft:anvil":6,"minecraft:azure_bluet":84,"minecraft:dark_oak_stairs":11,"minecraft:purple_carpet":107,"minecraft:black_candle":2,"minecraft:birch_wall_sign":1,"minecraft:azalea_leaves":20,"minecraft:brain_coral_block":23,"minecraft:green_bed":2,"minecraft:cyan_terracotta":2670,"minecraft:blackstone":29,"minecraft:dead_bubble_coral_block":1,"minecraft:polished_deepslate_stairs":76,"minecraft:soul_lantern":2,"minecraft:clay":464,"minecraft:calcite":516,"minecraft:poppy":52,"minecraft:chest":43,"minecraft:birch_wood":13,"minecraft:cobblestone":270,"minecraft:honeycomb_block":24,"minecraft:slime_block":6,"minecraft:iron_door":2,"minecraft:seagrass":42,"minecraft:nether_wart_block":43,"minecraft:birch_log":81,"minecraft:birch_trapdoor":23,"minecraft:orange_tulip":11,"minecraft:sand":2680,"minecraft:crimson_planks":2,"minecraft:netherrack":792,"minecraft:polished_deepslate_wall":16,"minecraft:oak_leaves":223,"minecraft:horn_coral_block":8,"minecraft:redstone_lamp":1,"minecraft:red_carpet":14,"minecraft:tuff":702,"minecraft:deepslate_diamond_ore":66,"minecraft:candle":10,"minecraft:black_banner":6,"minecraft:weeping_vines":1,"minecraft:polished_andesite_slab":3,"minecraft:mangrove_propagule":38,"minecraft:sandstone":66,"minecraft:rooted_dirt":43,"minecraft:large_fern":16,"minecraft:oak_trapdoor":7,"minecraft:spruce_sapling":11,"minecraft:furnace":19,"minecraft:carrots":409,"minecraft:acacia_stairs":16,"minecraft:dark_oak_fence_gate":42,"minecraft:stripped_spruce_log":159,"minecraft:bell":2,"minecraft:dead_horn_coral_block":1,"minecraft:polished_deepslate":272,"minecraft:lantern":39,"minecraft:crimson_door":2,"minecraft:stripped_jungle_log":3,"minecraft:packed_ice":241,"minecraft:stone":8333,"minecraft:white_tulip":21,"minecraft:yellow_shulker_box":2,"minecraft:podzol":204,"minecraft:light_blue_shulker_box":39,"minecraft:flowering_azalea":16,"minecraft:cut_copper_stairs":2,"minecraft:spruce_door":27,"minecraft:crafting_table":94,"minecraft:cyan_stained_glass_pane":8,"minecraft:rose_bush":19,"minecraft:andesite_slab":69,"minecraft:sculk_sensor":9,"minecraft:andesite_wall":24,"minecraft:lapis_ore":2,"minecraft:lily_pad":4,"minecraft:spruce_stairs":261,"minecraft:brick_slab":4,"minecraft:green_shulker_box":18,"minecraft:beehive":10,"minecraft:sweet_berry_bush":18,"minecraft:gray_bed":2,"minecraft:yellow_bed":21,"minecraft:dead_brain_coral_block":2,"minecraft:mangrove_slab":2,"minecraft:coal_ore":280,"minecraft:end_rod":75,"minecraft:bubble_coral_wall_fan":5,"minecraft:gray_carpet":3,"minecraft:terracotta":213,"minecraft:crimson_wall_sign":9,"minecraft:polished_andesite":15,"minecraft:birch_fence":13},"minecraft:dropped":{"minecraft:porkchop":2,"minecraft:glow_ink_sac":3,"minecraft:glass_bottle":6,"minecraft:diamond":1,"minecraft:crafting_table":1,"minecraft:cooked_porkchop":7,"minecraft:weeping_vines":3,"minecraft:glow_berries":2,"minecraft:cracked_stone_bricks":3,"minecraft:red_mushroom":2,"minecraft:emerald":5,"minecraft:gold_block":10,"minecraft:birch_fence":3,"minecraft:dark_oak_trapdoor":2,"minecraft:mangrove_stairs":1,"minecraft:netherite_boots":1,"minecraft:gold_nugget":9,"minecraft:sand":251,"minecraft:mangrove_slab":30,"minecraft:dark_oak_planks":4,"minecraft:white_wool":29,"minecraft:compass":2,"minecraft:diamond_block":1,"minecraft:iron_nugget":11,"minecraft:cobbled_deepslate":598,"minecraft:netherite_sword":2,"minecraft:wheat":8,"minecraft:obsidian":35,"minecraft:rotten_flesh":114,"minecraft:oak_planks":13,"minecraft:glowstone_dust":2,"minecraft:golden_shovel":1,"minecraft:sea_lantern":2,"minecraft:coal_ore":3,"minecraft:jungle_log":97,"minecraft:leather_boots":1,"minecraft:acacia_sapling":2,"minecraft:painting":3,"minecraft:glass":41,"minecraft:stone_brick_stairs":11,"minecraft:golden_boots":5,"minecraft:black_dye":9,"minecraft:wheat_seeds":1235,"minecraft:deepslate_redstone_ore":14,"minecraft:netherite_chestplate":2,"minecraft:prismarine_crystals":9,"minecraft:book":1,"minecraft:sheep_spawn_egg":1,"minecraft:golden_apple":6,"minecraft:lava_bucket":6,"minecraft:gray_wool":1,"minecraft:ink_sac":59,"minecraft:potion":2,"minecraft:pumpkin":1,"minecraft:golden_hoe":1,"minecraft:white_banner":2,"minecraft:chainmail_leggings":1,"minecraft:trapped_chest":2,"minecraft:acacia_planks":2,"minecraft:stone_brick_slab":4,"minecraft:snow_block":21,"minecraft:soul_soil":20,"minecraft:netherite_hoe":2,"minecraft:player_head":1,"minecraft:white_carpet":6,"minecraft:clay_ball":399,"minecraft:iron_boots":1,"minecraft:cobbled_deepslate_slab":4,"minecraft:white_terracotta":111,"minecraft:white_shulker_box":2,"minecraft:oak_sign":1,"minecraft:polished_deepslate_stairs":1,"minecraft:shears":2,"minecraft:diamond_sword":3,"minecraft:spruce_boat":7,"minecraft:sea_pickle":7,"minecraft:spruce_trapdoor":2,"minecraft:spruce_planks":125,"minecraft:diamond_pickaxe":4,"minecraft:andesite_stairs":8,"minecraft:popped_chorus_fruit":18,"minecraft:stone_bricks":51,"minecraft:bamboo":164,"minecraft:sandstone":34,"minecraft:bow":19,"minecraft:red_sand":5,"minecraft:terracotta":1,"minecraft:soul_sand":44,"minecraft:moss_block":9,"minecraft:mangrove_pressure_plate":3,"minecraft:oak_log":280,"minecraft:loom":1,"minecraft:ender_pearl":1501,"minecraft:dark_oak_sapling":57,"minecraft:leather":104,"minecraft:mangrove_planks":28,"minecraft:black_banner":8,"minecraft:cod":1,"minecraft:orange_glazed_terracotta":1,"minecraft:packed_ice":6,"minecraft:dark_oak_log":2,"minecraft:mutton":11,"minecraft:snowball":354,"minecraft:axolotl_bucket":1,"minecraft:andesite_slab":239,"minecraft:trident":2,"minecraft:mangrove_log":46,"minecraft:stone_brick_wall":1,"minecraft:birch_door":2,"minecraft:iron_ore":1,"minecraft:iron_bars":2,"minecraft:scaffolding":64,"minecraft:purple_carpet":14,"minecraft:bread":18,"minecraft:vine":1,"minecraft:golden_helmet":1,"minecraft:netherite_axe":2,"minecraft:mangrove_propagule":10,"minecraft:andesite_wall":3,"minecraft:amethyst_block":1,"minecraft:tropical_fish":11,"minecraft:spruce_stairs":18,"minecraft:acacia_log":4,"minecraft:iron_block":193,"minecraft:nether_wart_block":3,"minecraft:stonecutter":1,"minecraft:polished_basalt":2,"minecraft:redstone_block":54,"minecraft:polished_deepslate":4,"minecraft:blue_terracotta":78,"minecraft:kelp":11,"minecraft:sweet_berries":2,"minecraft:light_gray_terracotta":56,"minecraft:sculk_sensor":10,"minecraft:totem_of_undying":1,"minecraft:shulker_box":3,"minecraft:netherite_leggings":2,"minecraft:copper_ore":9,"minecraft:oak_button":3,"minecraft:andesite":4,"minecraft:golden_leggings":3,"minecraft:oak_sapling":46,"minecraft:birch_sign":1,"minecraft:spruce_log":676,"minecraft:light_blue_terracotta":37,"minecraft:brick":1,"minecraft:crimson_stem":4,"minecraft:clay":1,"minecraft:acacia_wood":47,"minecraft:oak_pressure_plate":2,"minecraft:cooked_beef":22,"minecraft:emerald_ore":1,"minecraft:crossbow":6,"minecraft:cookie":13,"minecraft:rooted_dirt":49,"minecraft:dark_oak_button":1,"minecraft:elytra":2,"minecraft:leather_helmet":1,"minecraft:red_carpet":1,"minecraft:packed_mud":1,"minecraft:dirt":725,"minecraft:stone_button":157,"minecraft:yellow_dye":1,"minecraft:chain":1,"minecraft:bone_meal":86,"minecraft:deepslate_coal_ore":4,"minecraft:sugar":31,"minecraft:bone":173,"minecraft:sugar_cane":746,"minecraft:polished_andesite_slab":6,"minecraft:white_bed":1,"minecraft:salmon":19,"minecraft:mangrove_fence":2,"minecraft:tipped_arrow":46,"minecraft:charcoal":1,"minecraft:honey_block":1,"minecraft:hopper":10,"minecraft:ladder":11,"minecraft:spruce_slab":6,"minecraft:white_dye":17,"minecraft:egg":1,"minecraft:enchanted_book":13,"minecraft:iron_ingot":54,"minecraft:netherite_pickaxe":3,"minecraft:sculk_shrieker":8,"minecraft:tnt":10,"minecraft:netherite_helmet":1,"minecraft:cobblestone":63,"minecraft:feather":20,"minecraft:oak_fence":1,"minecraft:iron_helmet":2,"minecraft:apple":6,"minecraft:granite":14,"minecraft:spruce_door":9,"minecraft:pufferfish":12,"minecraft:polished_andesite":25,"minecraft:end_rod":3,"minecraft:golden_carrot":3,"minecraft:diamond_helmet":4,"minecraft:lime_carpet":1,"minecraft:dried_kelp":59,"minecraft:paper":196,"minecraft:iron_shovel":3,"minecraft:string":628,"minecraft:gray_carpet":4,"minecraft:spruce_sapling":93,"minecraft:pink_tulip":1,"minecraft:moss_carpet":331,"minecraft:netherite_ingot":9,"minecraft:polished_diorite_slab":2,"minecraft:dark_oak_sign":2,"minecraft:deepslate":174,"minecraft:smooth_stone_slab":5,"minecraft:bowl":2,"minecraft:chicken":4,"minecraft:stone_slab":3,"minecraft:nether_bricks":27,"minecraft:spruce_fence":24,"minecraft:purple_stained_glass":3,"minecraft:hay_block":111,"minecraft:stone":1242,"minecraft:allium":3,"minecraft:crimson_slab":1,"minecraft:wooden_shovel":4,"minecraft:carved_pumpkin":2,"minecraft:spider_eye":13,"minecraft:rabbit_stew":1,"minecraft:magenta_dye":3,"minecraft:red_tulip":7,"minecraft:black_wool":15,"minecraft:quartz_slab":2,"minecraft:spruce_sign":2,"minecraft:brown_mushroom":1,"minecraft:birch_planks":4,"minecraft:diamond_axe":6,"minecraft:baked_potato":1,"minecraft:flint":16,"minecraft:cyan_terracotta":39,"minecraft:netherite_scrap":7,"minecraft:cornflower":4,"minecraft:cooked_cod":1,"minecraft:white_stained_glass_pane":2,"minecraft:pumpkin_pie":1,"minecraft:amethyst_shard":1,"minecraft:black_stained_glass":7,"minecraft:honeycomb_block":7,"minecraft:gravel":45,"minecraft:blackstone":29,"minecraft:mangrove_roots":525,"minecraft:honey_bottle":3,"minecraft:carrot":62,"minecraft:chiseled_stone_bricks":1,"minecraft:poppy":5,"minecraft:gunpowder":4462,"minecraft:skeleton_skull":3,"minecraft:azalea":10,"minecraft:chest":3,"minecraft:spruce_wood":3,"minecraft:basalt":5,"minecraft:arrow":176,"minecraft:prismarine_bricks":2,"minecraft:written_book":3,"minecraft:oak_leaves":27,"minecraft:netherrack":205,"minecraft:firework_rocket":65,"minecraft:water_bucket":5,"minecraft:stripped_spruce_log":1,"minecraft:purple_terracotta":1,"minecraft:mossy_cobblestone":3,"minecraft:diamond_leggings":5,"minecraft:lead":8,"minecraft:spectral_arrow":14,"minecraft:copper_ingot":4,"minecraft:grass_block":3,"minecraft:stick":480,"minecraft:blue_dye":2,"minecraft:torch":2,"minecraft:sculk_catalyst":1,"minecraft:map":11,"minecraft:iron_leggings":3,"minecraft:flowering_azalea":5,"minecraft:bucket":7,"minecraft:music_disc_cat":1,"minecraft:dandelion":8,"minecraft:smooth_basalt":12,"minecraft:redstone":180,"minecraft:coarse_dirt":17,"minecraft:raw_copper":34,"minecraft:tuff":116,"minecraft:raw_iron":1,"minecraft:light_gray_wool":1,"minecraft:iron_hoe":1,"minecraft:ender_eye":2490,"minecraft:glass_pane":18,"minecraft:filled_map":7,"minecraft:muddy_mangrove_roots":14,"minecraft:diamond_chestplate":3,"minecraft:iron_chestplate":1,"minecraft:quartz_stairs":1,"minecraft:mossy_stone_bricks":4,"minecraft:blue_ice":12,"minecraft:diamond_boots":5,"minecraft:slime_ball":4,"minecraft:raw_gold":1,"minecraft:dead_brain_coral_block":1,"minecraft:calcite":129,"minecraft:light_blue_shulker_box":1},"minecraft:used":{"minecraft:moss_block":66,"minecraft:dispenser":14,"minecraft:poppy":19,"minecraft:stone":2891,"minecraft:quartz_stairs":69,"minecraft:rotten_flesh":82,"minecraft:soul_sand":64,"minecraft:cocoa_beans":231,"minecraft:snowball":151,"minecraft:azure_bluet":305,"minecraft:spruce_boat":4,"minecraft:jungle_sapling":14,"minecraft:packed_ice":18,"minecraft:lava_bucket":28,"minecraft:mangrove_stairs":764,"minecraft:music_disc_ward":1,"minecraft:quartz_block":14,"minecraft:netherite_hoe":359,"minecraft:dark_oak_slab":157,"minecraft:netherite_boots":4,"minecraft:bow":250,"minecraft:mangrove_slab":32,"minecraft:cooked_cod":70,"minecraft:oak_sapling":143,"minecraft:mossy_stone_bricks":76,"minecraft:damaged_anvil":1,"minecraft:mossy_stone_brick_stairs":2,"minecraft:composter":14,"minecraft:clay":117,"minecraft:glow_berries":8,"minecraft:blast_furnace":7,"minecraft:purple_terracotta":311,"minecraft:birch_fence":60,"minecraft:birch_slab":581,"minecraft:zombie_head":4,"minecraft:deepslate_iron_ore":9,"minecraft:oak_pressure_plate":1,"minecraft:flowering_azalea_leaves":25,"minecraft:nether_wart_block":17,"minecraft:diamond_sword":438,"minecraft:smithing_table":1,"minecraft:birch_log":20,"minecraft:oak_boat":1,"minecraft:waxed_cut_copper_stairs":43,"minecraft:oak_trapdoor":35,"minecraft:polished_blackstone_brick_slab":180,"minecraft:carved_pumpkin":23,"minecraft:light_gray_carpet":2,"minecraft:tinted_glass":3,"minecraft:mangrove_fence":1,"minecraft:torch":663,"minecraft:mud_brick_stairs":29,"minecraft:oak_fence_gate":66,"minecraft:sea_lantern":334,"minecraft:chipped_anvil":3,"minecraft:iron_block":607,"minecraft:polished_deepslate_wall":26,"minecraft:jungle_log":51,"minecraft:barrel":21,"minecraft:bamboo":98,"minecraft:basalt":293,"minecraft:trapped_chest":15,"minecraft:horn_coral_fan":7,"minecraft:calcite":88,"minecraft:wheat_seeds":2230,"minecraft:light_blue_shulker_box":40,"minecraft:tube_coral_block":5,"minecraft:birch_planks":24,"minecraft:lead":1,"minecraft:cauldron":4,"minecraft:spruce_fence_gate":35,"minecraft:glow_ink_sac":6,"minecraft:leather_boots":1,"minecraft:gold_ore":6,"minecraft:polished_deepslate_slab":437,"minecraft:red_bed":25,"minecraft:crimson_trapdoor":55,"minecraft:sculk_shrieker":1,"minecraft:white_bed":25,"minecraft:campfire":23,"minecraft:spruce_log":2183,"minecraft:amethyst_cluster":30,"minecraft:diamond_pickaxe":11274,"minecraft:warped_trapdoor":2,"minecraft:diamond_shovel":1492,"minecraft:mangrove_pressure_plate":5,"minecraft:oak_button":34,"minecraft:spruce_pressure_plate":4,"minecraft:spruce_trapdoor":926,"minecraft:spruce_sapling":203,"minecraft:potion":3,"minecraft:azalea_leaves":18,"minecraft:orange_banner":1,"minecraft:purple_bed":14,"minecraft:crimson_stairs":14,"minecraft:cooked_porkchop":84,"minecraft:porkchop":3,"minecraft:andesite_stairs":46,"minecraft:stripped_oak_log":17,"minecraft:dandelion":18,"minecraft:moss_carpet":111,"minecraft:blue_terracotta":876,"minecraft:red_sand":3,"minecraft:polished_deepslate":986,"minecraft:light_gray_stained_glass_pane":12,"minecraft:bone_block":149,"minecraft:polished_basalt":874,"minecraft:mossy_stone_brick_slab":4,"minecraft:spruce_leaves":7,"minecraft:mutton":6,"minecraft:jungle_planks":8,"minecraft:beehive":14,"minecraft:obsidian":178,"minecraft:honey_bottle":12,"minecraft:mangrove_log":11,"minecraft:bricks":23,"minecraft:spruce_wood":131,"minecraft:lantern":129,"minecraft:polished_blackstone_brick_wall":115,"minecraft:item_frame":66,"minecraft:deepslate_diamond_ore":28,"minecraft:birch_trapdoor":116,"minecraft:written_book":1,"minecraft:mangrove_roots":1,"minecraft:blue_shulker_box":30,"minecraft:gold_block":36,"minecraft:skeleton_skull":11,"minecraft:dark_oak_sapling":38,"minecraft:tube_coral_fan":6,"minecraft:end_rod":152,"minecraft:diamond_boots":1,"minecraft:wither_skeleton_skull":4,"minecraft:gray_carpet":5,"minecraft:stone_pickaxe":356,"minecraft:mangrove_planks":81,"minecraft:oak_planks":34,"minecraft:sandstone":46,"minecraft:sugar_cane":343,"minecraft:diamond_axe":631,"minecraft:white_wool":8,"minecraft:netherite_leggings":5,"minecraft:crossbow":6,"minecraft:end_stone":1,"minecraft:sticky_piston":4,"minecraft:lever":26,"minecraft:daylight_detector":2,"minecraft:dark_oak_log":317,"minecraft:bread":202,"minecraft:iron_door":3,"minecraft:deepslate":766,"minecraft:cooked_rabbit":9,"minecraft:chain":31,"minecraft:smooth_stone_slab":473,"minecraft:coarse_dirt":69,"minecraft:bone_meal":266,"minecraft:netherite_sword":3906,"minecraft:rose_bush":17,"minecraft:white_tulip":12,"minecraft:flint_and_steel":14,"minecraft:redstone":260,"minecraft:ender_chest":12,"minecraft:brown_shulker_box":25,"minecraft:stone_hoe":543,"minecraft:cooked_chicken":17,"minecraft:dirt":2693,"minecraft:bee_nest":12,"minecraft:spruce_fence":151,"minecraft:iron_hoe":11,"minecraft:oak_stairs":28,"minecraft:crimson_slab":91,"minecraft:iron_boots":3,"minecraft:soul_soil":58,"minecraft:waxed_cut_copper_slab":34,"minecraft:black_stained_glass":9,"minecraft:deepslate_tile_stairs":72,"minecraft:netherite_pickaxe":22384,"minecraft:cooked_beef":121,"minecraft:mossy_stone_brick_wall":2,"minecraft:pumpkin":8,"minecraft:iron_leggings":1,"minecraft:cobblestone_stairs":217,"minecraft:snow_block":7,"minecraft:baked_potato":16,"minecraft:brown_mushroom":8,"minecraft:spruce_sign":33,"minecraft:music_disc_cat":4,"minecraft:red_mushroom":4,"minecraft:spider_eye":2,"minecraft:piston":156,"minecraft:flower_pot":1,"minecraft:stone_slab":183,"minecraft:stone_axe":844,"minecraft:fire_coral_block":6,"minecraft:cobbled_deepslate_slab":106,"minecraft:pumpkin_pie":9,"minecraft:wither_rose":2,"minecraft:sea_pickle":17,"minecraft:sculk_catalyst":1,"minecraft:birch_stairs":20,"minecraft:polished_blackstone":8,"minecraft:spruce_slab":1055,"minecraft:ladder":114,"minecraft:chest":139,"minecraft:white_shulker_box":10,"minecraft:brick_slab":42,"minecraft:allium":76,"minecraft:acacia_sapling":2,"minecraft:stripped_spruce_log":136,"minecraft:honey_block":22,"minecraft:netherite_shovel":3080,"minecraft:black_stained_glass_pane":19,"minecraft:birch_sapling":30,"minecraft:grass_block":110,"minecraft:orange_shulker_box":5,"minecraft:copper_ore":20,"minecraft:wet_sponge":14,"minecraft:dark_oak_button":1,"minecraft:stone_brick_stairs":422,"minecraft:rabbit_stew":1,"minecraft:red_stained_glass_pane":52,"minecraft:dark_oak_boat":1,"minecraft:sweet_berries":86,"minecraft:furnace":30,"minecraft:egg":234,"minecraft:potato":326,"minecraft:emerald_ore":1,"minecraft:spruce_door":49,"minecraft:orange_tulip":9,"minecraft:oak_leaves":22,"minecraft:cookie":71,"minecraft:dark_oak_trapdoor":6,"minecraft:sand":405,"minecraft:blue_ice":5,"minecraft:netherite_helmet":4,"minecraft:deepslate_tiles":9,"minecraft:crying_obsidian":1,"minecraft:stone_button":9,"minecraft:soul_lantern":6,"minecraft:fire_charge":5,"minecraft:dark_oak_fence":43,"minecraft:bubble_coral_block":3,"minecraft:gray_stained_glass":950,"minecraft:iron_bars":280,"minecraft:stone_sword":151,"minecraft:brain_coral_fan":2,"minecraft:sandstone_wall":11,"minecraft:netherrack":341,"minecraft:anvil":10,"minecraft:target":1,"minecraft:chorus_flower":1,"minecraft:stone_stairs":36,"minecraft:nether_brick_stairs":9,"minecraft:polished_diorite":1,"minecraft:shroomlight":25,"minecraft:red_shulker_box":109,"minecraft:flowering_azalea":3,"minecraft:iron_axe":2384,"minecraft:rooted_dirt":10,"minecraft:spruce_button":4,"minecraft:slime_block":11,"minecraft:totem_of_undying":1,"minecraft:mud_bricks":94,"minecraft:glowstone":12,"minecraft:beef":8,"minecraft:cobbled_deepslate":3069,"minecraft:observer":222,"minecraft:pointed_dripstone":4,"minecraft:crimson_stem":42,"minecraft:water_bucket":1531,"minecraft:yellow_shulker_box":2,"minecraft:bubble_coral_fan":5,"minecraft:polished_blackstone_bricks":9,"minecraft:cracked_stone_bricks":62,"minecraft:salmon":6,"minecraft:mossy_cobblestone":34,"minecraft:lime_terracotta":62,"minecraft:comparator":16,"minecraft:vine":16,"minecraft:tnt":30,"minecraft:crafting_table":107,"minecraft:oak_slab":102,"minecraft:birch_sign":9,"minecraft:cod":13,"minecraft:dark_oak_fence_gate":94,"minecraft:lime_shulker_box":33,"minecraft:cake":1,"minecraft:oak_log":942,"minecraft:mud":136,"minecraft:dark_prismarine":2,"minecraft:ender_eye":60,"minecraft:cornflower":15,"minecraft:stripped_jungle_log":2,"minecraft:mangrove_propagule":74,"minecraft:sunflower":11,"minecraft:iron_pickaxe":1013,"minecraft:crimson_sign":14,"minecraft:chiseled_stone_bricks":1,"minecraft:cobblestone":537,"minecraft:glass_pane":64,"minecraft:brown_mushroom_block":7,"minecraft:jukebox":4,"minecraft:kelp":365,"minecraft:candle":5,"minecraft:light_gray_dye":1,"minecraft:iron_shovel":903,"minecraft:shield":1146,"minecraft:white_terracotta":34,"minecraft:iron_sword":115,"minecraft:purple_shulker_box":7,"minecraft:bell":4,"minecraft:player_head":36,"minecraft:sculk_sensor":1,"minecraft:iron_chestplate":1,"minecraft:nether_bricks":164,"minecraft:carrot":777,"minecraft:deepslate_tile_slab":30,"minecraft:tuff":120,"minecraft:axolotl_bucket":38,"minecraft:milk_bucket":6,"minecraft:polished_deepslate_stairs":236,"minecraft:glass":2208,"minecraft:cyan_terracotta":1739,"minecraft:coal_ore":106,"minecraft:quartz_slab":12,"minecraft:packed_mud":22,"minecraft:iron_helmet":3,"minecraft:dark_oak_wood":372,"minecraft:crimson_roots":2,"minecraft:stone_bricks":1148,"minecraft:red_carpet":16,"minecraft:redstone_lamp":1,"minecraft:honeycomb_block":19,"minecraft:magma_block":2,"minecraft:hay_block":309,"minecraft:scaffolding":88,"minecraft:gray_bed":1,"minecraft:beetroot_seeds":340,"minecraft:polished_diorite_stairs":77,"minecraft:polished_blackstone_stairs":4,"minecraft:chiseled_polished_blackstone":2,"minecraft:dark_oak_stairs":23,"minecraft:dark_oak_sign":1,"minecraft:birch_wood":73,"minecraft:ender_pearl":107,"minecraft:yellow_terracotta":1,"minecraft:black_banner":48,"minecraft:loom":2,"minecraft:light_gray_terracotta":83,"minecraft:sponge":1,"minecraft:stone_brick_wall":642,"minecraft:shears":123,"minecraft:firework_rocket":2102,"minecraft:birch_fence_gate":30,"minecraft:melon_slice":5,"minecraft:string":14,"minecraft:gravel":130,"minecraft:golden_helmet":1,"minecraft:grindstone":1,"minecraft:crimson_door":2,"minecraft:deepslate_coal_ore":11,"minecraft:andesite":355,"minecraft:air":1,"minecraft:tropical_fish_bucket":17,"minecraft:azalea":12,"minecraft:oak_fence":70,"minecraft:tropical_fish":3,"minecraft:stone_shovel":968,"minecraft:light_blue_terracotta":771,"minecraft:spruce_planks":818,"minecraft:wooden_shovel":649,"minecraft:cut_copper_stairs":6,"minecraft:white_carpet":70,"minecraft:hopper":268,"minecraft:spruce_stairs":792,"minecraft:shulker_box":39,"minecraft:granite":9,"minecraft:birch_door":2,"minecraft:andesite_wall":165,"minecraft:stone_brick_slab":159,"minecraft:dark_oak_planks":29,"minecraft:red_tulip":10,"minecraft:acacia_slab":4,"minecraft:polished_blackstone_brick_stairs":4,"minecraft:crimson_planks":1,"minecraft:golden_carrot":15,"minecraft:white_stained_glass_pane":78,"minecraft:horn_coral_block":4,"minecraft:brain_coral_block":9,"minecraft:cooked_mutton":15,"minecraft:pink_tulip":2,"minecraft:iron_ore":35,"minecraft:amethyst_block":62,"minecraft:glass_bottle":44,"minecraft:polished_andesite":73,"minecraft:andesite_slab":138,"minecraft:black_shulker_box":61,"minecraft:stonecutter":17,"minecraft:beacon":2,"minecraft:cobblestone_slab":501,"minecraft:glow_item_frame":1,"minecraft:terracotta":92,"minecraft:painting":21,"minecraft:smoker":1,"minecraft:purple_stained_glass":13,"minecraft:apple":39,"minecraft:cracked_polished_blackstone_bricks":73,"minecraft:map":38,"minecraft:netherite_axe":3038,"minecraft:fishing_rod":58,"minecraft:green_shulker_box":18,"minecraft:white_banner":11,"minecraft:mud_brick_wall":83,"minecraft:bucket":1620,"minecraft:yellow_bed":22,"minecraft:purple_carpet":200,"minecraft:smooth_stone":219},"minecraft:broken":{"minecraft:wooden_shovel":11,"minecraft:iron_leggings":1,"minecraft:crossbow":1,"minecraft:stone_hoe":4,"minecraft:shield":4,"minecraft:iron_pickaxe":3,"minecraft:iron_shovel":3,"minecraft:leather_leggings":1,"minecraft:stone_pickaxe":2,"minecraft:stone_axe":7,"minecraft:stone_shovel":7,"minecraft:iron_boots":1,"minecraft:chainmail_boots":1,"minecraft:stone_sword":1,"minecraft:iron_axe":10,"minecraft:iron_helmet":1,"minecraft:leather_chestplate":1,"minecraft:leather_boots":1},"minecraft:killed":{"minecraft:guardian":4,"minecraft:tropical_fish":7,"minecraft:elder_guardian":1,"minecraft:iron_golem":1,"minecraft:pillager":54,"minecraft:donkey":1,"minecraft:zombie":144,"minecraft:evoker":1,"minecraft:vindicator":25,"minecraft:witch":6,"minecraft:spider":37,"minecraft:wither":1,"minecraft:piglin":10,"minecraft:zombie_villager":7,"minecraft:sheep":27,"minecraft:trader_llama":6,"minecraft:mooshroom":12,"minecraft:ghast":2,"minecraft:vex":2,"minecraft:slime":7,"minecraft:drowned":8,"minecraft:hoglin":6,"minecraft:squid":20,"minecraft:villager":11,"minecraft:skeleton":111,"minecraft:chicken":6,"minecraft:glow_squid":6,"minecraft:cow":86,"minecraft:horse":4,"minecraft:wandering_trader":1,"minecraft:enderman":3643,"minecraft:pig":5,"minecraft:creeper":87,"minecraft:stray":83,"minecraft:blaze":99}},"DataVersion":3465}