{"stats":{"minecraft:custom":{"minecraft:jump":78,"minecraft:open_chest":5,"minecraft:time_since_rest":8877,"minecraft:damage_dealt":87,"minecraft:play_time":8877,"minecraft:leave_game":2,"minecraft:sprint_one_cm":38712,"minecraft:damage_taken":10,"minecraft:time_since_death":8877,"minecraft:walk_one_cm":36051,"minecraft:climb_one_cm":300,"minecraft:total_world_time":8877,"minecraft:talked_to_villager":1,"minecraft:fall_one_cm":544,"minecraft:fly_one_cm":7264,"minecraft:open_barrel":1},"minecraft:used":{"minecraft:potato":1}},"DataVersion":2975}