{"stats":{"minecraft:killed":{"minecraft:polar_bear":1},"minecraft:picked_up":{"minecraft:arrow":1,"minecraft:bone":1},"minecraft:custom":{"minecraft:jump":177,"minecraft:open_chest":1,"minecraft:time_since_rest":16012,"minecraft:leave_game":1,"minecraft:damage_dealt":423,"minecraft:damage_taken":451,"minecraft:sprint_one_cm":22418,"minecraft:play_time":16012,"minecraft:walk_on_water_one_cm":2092,"minecraft:time_since_death":16012,"minecraft:walk_one_cm":33044,"minecraft:total_world_time":16012,"minecraft:walk_under_water_one_cm":1180,"minecraft:mob_kills":1,"minecraft:swim_one_cm":1442,"minecraft:fall_one_cm":894,"minecraft:fly_one_cm":21059},"minecraft:used":{"minecraft:stone_sword":23}},"DataVersion":3120}