{"stats":{"minecraft:killed_by":{"minecraft:husk":2,"minecraft:skeleton":1,"minecraft:pillager":1},"minecraft:dropped":{"minecraft:baked_potato":10,"minecraft:stone_sword":2},"minecraft:mined":{"minecraft:large_fern":1,"minecraft:sweet_berry_bush":2,"minecraft:crafting_table":1,"minecraft:grass":136,"minecraft:oak_log":9,"minecraft:tall_grass":10,"minecraft:spruce_leaves":14,"minecraft:blue_orchid":1,"minecraft:sugar_cane":2,"minecraft:oak_planks":6,"minecraft:oak_leaves":2},"minecraft:killed":{"minecraft:skeleton":1,"minecraft:sheep":3,"minecraft:panda":1,"minecraft:spider":2,"minecraft:tropical_fish":2},"minecraft:picked_up":{"minecraft:stick":4,"minecraft:crafting_table":1,"minecraft:sweet_berries":52,"minecraft:oak_log":9,"minecraft:spruce_sapling":1,"minecraft:spruce_log":7,"minecraft:string":4,"minecraft:bone":2,"minecraft:stone_sword":2,"minecraft:arrow":2,"minecraft:blue_orchid":1,"minecraft:tropical_fish":1,"minecraft:wheat_seeds":13,"minecraft:oak_boat":1,"minecraft:baked_potato":10,"minecraft:bamboo":1,"minecraft:oak_sapling":7,"minecraft:sugar_cane":4,"minecraft:mutton":5,"minecraft:oak_planks":6,"minecraft:white_wool":4},"minecraft:custom":{"minecraft:time_since_rest":104,"minecraft:sprint_one_cm":80362,"minecraft:walk_one_cm":79708,"minecraft:damage_taken":1648,"minecraft:damage_absorbed":80,"minecraft:damage_blocked_by_shield":1645,"minecraft:mob_kills":11,"minecraft:drop":12,"minecraft:damage_dealt":1662,"minecraft:swim_one_cm":7006,"minecraft:talked_to_villager":2,"minecraft:interact_with_crafting_table":1,"minecraft:fly_one_cm":48452,"minecraft:open_chest":1,"minecraft:crouch_one_cm":2773,"minecraft:play_time":26742,"minecraft:deaths":4,"minecraft:sneak_time":872,"minecraft:walk_under_water_one_cm":3534,"minecraft:boat_one_cm":4937,"minecraft:jump":312,"minecraft:leave_game":1,"minecraft:time_since_death":84,"minecraft:walk_on_water_one_cm":5622,"minecraft:sleep_in_bed":1,"minecraft:total_world_time":26742,"minecraft:fall_one_cm":7529},"minecraft:used":{"minecraft:stone_sword":183,"minecraft:stone_shovel":1,"minecraft:baked_potato":9,"minecraft:oak_planks":37,"minecraft:shield":39,"minecraft:stone_axe":24,"minecraft:crafting_table":1,"minecraft:white_bed":1,"minecraft:oak_boat":1},"minecraft:crafted":{"minecraft:oak_boat":1,"minecraft:oak_planks":40,"minecraft:crafting_table":1}},"DataVersion":3120}