{"stats":{"minecraft:custom":{"minecraft:jump":45,"minecraft:time_since_rest":7996,"minecraft:leave_game":1,"minecraft:crouch_one_cm":44,"minecraft:interact_with_furnace":1,"minecraft:sprint_one_cm":10430,"minecraft:play_time":7996,"minecraft:time_since_death":7996,"minecraft:walk_one_cm":34136,"minecraft:sneak_time":537,"minecraft:climb_one_cm":8130,"minecraft:total_world_time":7996,"minecraft:fall_one_cm":954,"minecraft:fly_one_cm":9873},"minecraft:mined":{"minecraft:coal_ore":1,"minecraft:stone":2,"minecraft:deepslate":3},"minecraft:crafted":{"minecraft:torch":4,"minecraft:oak_planks":4,"minecraft:stick":8},"minecraft:picked_up":{"minecraft:cobbled_deepslate":3,"minecraft:coal":1,"minecraft:cobblestone":2},"minecraft:used":{"minecraft:stone_pickaxe":6}},"DataVersion":3465}