{"stats":{"minecraft:custom":{"minecraft:jump":335,"minecraft:time_since_rest":2139,"minecraft:damage_dealt":10,"minecraft:deaths":1,"minecraft:damage_taken":270,"minecraft:leave_game":3,"minecraft:play_time":6954,"minecraft:sprint_one_cm":45347,"minecraft:time_since_death":2119,"minecraft:walk_on_water_one_cm":535,"minecraft:walk_one_cm":15662,"minecraft:total_world_time":6954,"minecraft:climb_one_cm":1512,"minecraft:walk_under_water_one_cm":2993,"minecraft:swim_one_cm":1935,"minecraft:fall_one_cm":8842,"minecraft:fly_one_cm":75734},"minecraft:picked_up":{"minecraft:egg":1},"minecraft:used":{"minecraft:egg":1}},"DataVersion":3120}