{"stats":{"minecraft:picked_up":{"minecraft:sweet_berries":22},"minecraft:custom":{"minecraft:time_since_rest":8618,"minecraft:open_chest":1,"minecraft:crouch_one_cm":563,"minecraft:walk_one_cm":305199,"minecraft:play_time":82594,"minecraft:sprint_one_cm":323499,"minecraft:open_enderchest":2,"minecraft:damage_taken":650,"minecraft:deaths":2,"minecraft:sneak_time":372,"minecraft:walk_under_water_one_cm":11666,"minecraft:jump":349,"minecraft:damage_dealt":50,"minecraft:leave_game":1,"minecraft:time_since_death":32383,"minecraft:walk_on_water_one_cm":13448,"minecraft:total_world_time":82594,"minecraft:climb_one_cm":5312,"minecraft:damage_resisted":18,"minecraft:swim_one_cm":1458,"minecraft:interact_with_crafting_table":1,"minecraft:fall_one_cm":5128,"minecraft:fly_one_cm":33710,"minecraft:horse_one_cm":366},"minecraft:killed_by":{"minecraft:spider":1},"minecraft:mined":{"minecraft:grass":1},"minecraft:used":{"minecraft:stone_sword":2,"minecraft:written_book":3,"minecraft:carrot":15}},"DataVersion":2975}