{"stats":{"minecraft:killed_by":{"minecraft:polar_bear":1},"minecraft:custom":{"minecraft:jump":67,"minecraft:time_since_rest":141,"minecraft:leave_game":1,"minecraft:damage_dealt":88,"minecraft:crouch_one_cm":303,"minecraft:deaths":1,"minecraft:sprint_one_cm":17146,"minecraft:play_time":2869,"minecraft:damage_taken":270,"minecraft:time_since_death":121,"minecraft:walk_one_cm":17865,"minecraft:sneak_time":72,"minecraft:total_world_time":2869,"minecraft:fall_one_cm":4718,"minecraft:fly_one_cm":31061}},"DataVersion":2865}