{"stats":{"minecraft:picked_up":{"minecraft:wooden_axe":2,"minecraft:birch_log":22,"minecraft:andesite":109,"minecraft:flint":6,"minecraft:tuff":159,"minecraft:oak_log":151,"minecraft:lapis_lazuli":58,"minecraft:string":3,"minecraft:dirt":13,"minecraft:raw_copper":37,"minecraft:apple":3,"minecraft:wheat_seeds":1,"minecraft:raw_gold":5,"minecraft:cobbled_deepslate":1275,"minecraft:stone_pickaxe":5,"minecraft:white_tulip":1,"minecraft:iron_pickaxe":1,"minecraft:birch_sapling":2,"minecraft:egg":1,"minecraft:stick":63,"minecraft:raw_iron":11,"minecraft:torch":6,"minecraft:gravel":57,"minecraft:spruce_sapling":25,"minecraft:diorite":15,"minecraft:spruce_log":123,"minecraft:redstone":327,"minecraft:spider_eye":2,"minecraft:diamond":9,"minecraft:granite":3,"minecraft:oak_sapling":49,"minecraft:coal":49,"minecraft:cobblestone":390},"minecraft:custom":{"minecraft:interact_with_furnace":19,"minecraft:mob_kills":3,"minecraft:interact_with_crafting_table":12,"minecraft:interact_with_stonecutter":1,"minecraft:leave_game":4,"minecraft:time_since_death":18175,"minecraft:climb_one_cm":20006,"minecraft:time_since_rest":18195,"minecraft:sprint_one_cm":82783,"minecraft:damage_taken":1828,"minecraft:walk_one_cm":820702,"minecraft:drop":21,"minecraft:damage_dealt":623,"minecraft:fly_one_cm":39235,"minecraft:open_chest":43,"minecraft:crouch_one_cm":798,"minecraft:play_time":189722,"minecraft:deaths":4,"minecraft:sneak_time":405,"minecraft:walk_under_water_one_cm":5875,"minecraft:jump":1756,"minecraft:walk_on_water_one_cm":12531,"minecraft:total_world_time":189722,"minecraft:fall_one_cm":22975},"minecraft:killed_by":{"minecraft:skeleton":2,"minecraft:witch":1,"minecraft:zombie":1},"minecraft:dropped":{"minecraft:wheat_seeds":1,"minecraft:cobblestone":1,"minecraft:dirt":2,"minecraft:wooden_axe":2,"minecraft:spider_eye":1,"minecraft:stone_pickaxe":9,"minecraft:iron_pickaxe":1,"minecraft:string":2,"minecraft:written_book":3,"minecraft:egg":1},"minecraft:crafted":{"minecraft:deepslate":128,"minecraft:crafting_table":1,"minecraft:spruce_planks":176,"minecraft:wooden_pickaxe":2,"minecraft:furnace":1,"minecraft:copper_ingot":64,"minecraft:air":0,"minecraft:iron_axe":3,"minecraft:stick":152,"minecraft:iron_ingot":11,"minecraft:iron_pickaxe":11,"minecraft:stone_pickaxe":8,"minecraft:wooden_axe":2,"minecraft:gold_ingot":5,"minecraft:torch":64},"minecraft:mined":{"minecraft:deepslate_redstone_ore":72,"minecraft:tuff":209,"minecraft:deepslate_diamond_ore":9,"minecraft:granite":3,"minecraft:grass_block":6,"minecraft:copper_ore":10,"minecraft:cobblestone":3,"minecraft:spruce_leaves":29,"minecraft:deepslate_gold_ore":5,"minecraft:diorite":16,"minecraft:wall_torch":6,"minecraft:iron_ore":6,"minecraft:cobbled_deepslate":1,"minecraft:spruce_log":11,"minecraft:andesite":109,"minecraft:deepslate_lapis_ore":8,"minecraft:grass":9,"minecraft:coal_ore":49,"minecraft:deepslate_iron_ore":5,"minecraft:gravel":63,"minecraft:dirt":7,"minecraft:white_tulip":1,"minecraft:stone":386,"minecraft:oak_leaves":3,"minecraft:deepslate":1451},"minecraft:used":{"minecraft:stone_sword":38,"minecraft:stone_pickaxe":582,"minecraft:wooden_pickaxe":41,"minecraft:torch":64,"minecraft:dirt":4,"minecraft:crafting_table":1,"minecraft:red_bed":1,"minecraft:carrot":20,"minecraft:tuff":32,"minecraft:wooden_axe":8,"minecraft:iron_axe":30,"minecraft:iron_pickaxe":1745,"minecraft:spruce_sapling":25,"minecraft:cobblestone":41,"minecraft:oak_sapling":49,"minecraft:cobbled_deepslate":16},"minecraft:killed":{"minecraft:spider":2,"minecraft:zombie":1},"minecraft:broken":{"minecraft:stone_pickaxe":4,"minecraft:iron_pickaxe":6}},"DataVersion":2975}