{"stats":{"minecraft:used":{"minecraft:water_bucket":2,"minecraft:leather_leggings":1,"minecraft:stone_sword":24,"minecraft:stone_shovel":4,"minecraft:stone_pickaxe":47,"minecraft:oak_planks":48,"minecraft:leather_chestplate":1,"minecraft:wooden_pickaxe":13,"minecraft:shield":4,"minecraft:leather_boots":1,"minecraft:sand":1,"minecraft:crafting_table":6,"minecraft:carrot":15,"minecraft:leather_helmet":1,"minecraft:stone_axe":82,"minecraft:cobblestone":4,"minecraft:sweet_berries":2,"minecraft:furnace":1,"minecraft:bucket":3},"minecraft:picked_up":{"minecraft:crafting_table":5,"minecraft:leather":4,"minecraft:oak_log":129,"minecraft:lapis_lazuli":26,"minecraft:dirt":18,"minecraft:bone":1,"minecraft:bow":1,"minecraft:wheat_seeds":11,"minecraft:spruce_planks":10,"minecraft:iron_ingot":2,"minecraft:beef":7,"minecraft:oak_planks":92,"minecraft:furnace":1,"minecraft:raw_iron":7,"minecraft:pumpkin":8,"minecraft:sweet_berries":13,"minecraft:gravel":3,"minecraft:sand":1,"minecraft:spruce_log":687,"minecraft:arrow":2,"minecraft:oak_sapling":1,"minecraft:mutton":3,"minecraft:white_wool":2,"minecraft:cobblestone":47},"minecraft:crafted":{"minecraft:oak_planks":392,"minecraft:stone_shovel":1,"minecraft:crafting_table":3,"minecraft:spruce_planks":76,"minecraft:wooden_pickaxe":1,"minecraft:furnace":1,"minecraft:bucket":1,"minecraft:stone_axe":9,"minecraft:air":0,"minecraft:stick":24,"minecraft:iron_ingot":4,"minecraft:stone_pickaxe":1},"minecraft:killed":{"minecraft:sheep":2,"minecraft:skeleton":2,"minecraft:cow":3},"minecraft:mined":{"minecraft:podzol":2,"minecraft:crafting_table":5,"minecraft:allium":1,"minecraft:grass_block":1,"minecraft:diorite":1,"minecraft:furnace":1,"minecraft:iron_ore":7,"minecraft:sweet_berry_bush":2,"minecraft:spruce_log":64,"minecraft:birch_leaves":1,"minecraft:pumpkin":11,"minecraft:deepslate_lapis_ore":4,"minecraft:grass":64,"minecraft:oak_log":4,"minecraft:sand":1,"minecraft:gravel":3,"minecraft:dirt":6,"minecraft:stone":43,"minecraft:deepslate":1},"minecraft:dropped":{"minecraft:gravel":3,"minecraft:iron_ingot":2,"minecraft:stone_axe":2,"minecraft:sweet_berries":11,"minecraft:wheat_seeds":12,"minecraft:cobblestone":4,"minecraft:oak_planks":380,"minecraft:dirt":18,"minecraft:spruce_planks":20,"minecraft:oak_sapling":1,"minecraft:pumpkin":8,"minecraft:spruce_log":158,"minecraft:wooden_pickaxe":1,"minecraft:white_wool":2,"minecraft:bone":1},"minecraft:custom":{"minecraft:interact_with_furnace":7,"minecraft:mob_kills":7,"minecraft:interact_with_crafting_table":13,"minecraft:eat_cake_slice":5,"minecraft:leave_game":4,"minecraft:time_since_death":37687,"minecraft:sleep_in_bed":1,"minecraft:climb_one_cm":1156,"minecraft:time_since_rest":33762,"minecraft:sprint_one_cm":165206,"minecraft:damage_taken":320,"minecraft:walk_one_cm":198871,"minecraft:damage_blocked_by_shield":180,"minecraft:drop":30,"minecraft:damage_dealt":1005,"minecraft:swim_one_cm":7944,"minecraft:talked_to_villager":1,"minecraft:fly_one_cm":331970,"minecraft:open_chest":1,"minecraft:crouch_one_cm":7572,"minecraft:play_time":37687,"minecraft:sneak_time":1588,"minecraft:walk_under_water_one_cm":7621,"minecraft:boat_one_cm":1190,"minecraft:jump":1235,"minecraft:walk_on_water_one_cm":10496,"minecraft:total_world_time":37687,"minecraft:fall_one_cm":42050,"minecraft:horse_one_cm":5744}},"DataVersion":3105}